{
     "1": {
          "Time": "09:51:32.039",
          "ac_flowrate": 0.0,
          "cp_flowrate": 0.0,
          "cp_pressure": 0.062,
          "cp_temperature": 0.0,
          "mixer_motor_temperature_M1": 14.8,
          "mixer_motor_temperature_M2": 16.6,
          "mixer_pressure": 0.197,
          "mixer_speed_M1": 0.0,
          "mixer_speed_M2": 0.0,
          "mixer_temperature_Funnel": 24.6,
          "mixer_temperature_Funnel_outlet": 25.1,
          "mixer_temperature_Funnel_plate": 24.5,
          "mixer_torque_M1": 0.113,
          "mixer_torque_M2": 0.038
     },
     "2": {
          "Time": "09:51:33.139",
          "ac_flowrate": 0.0,
          "cp_flowrate": 0.0,
          "cp_pressure": 0.0,
          "cp_temperature": 0.0,
          "mixer_motor_temperature_M1": 14.5,
          "mixer_motor_temperature_M2": 16.3,
          "mixer_pressure": 0.171,
          "mixer_speed_M1": 0.0,
          "mixer_speed_M2": 0.0,
          "mixer_temperature_Funnel": 24.6,
          "mixer_temperature_Funnel_outlet": 27.1,
          "mixer_temperature_Funnel_plate": 26.0,
          "mixer_torque_M1": 0.113,
          "mixer_torque_M2": 0.113
     },
     "3": {
          "Time": "09:51:34.256",
          "ac_flowrate": 0.0,
          "cp_flowrate": 0.0,
          "cp_pressure": 0.016,
          "cp_temperature": 0.0,
          "mixer_motor_temperature_M1": 14.8,
          "mixer_motor_temperature_M2": 16.8,
          "mixer_pressure": 0.198,
          "mixer_speed_M1": 0.0,
          "mixer_speed_M2": 0.0,
          "mixer_temperature_Funnel": 26.0,
          "mixer_temperature_Funnel_outlet": 25.1,
          "mixer_temperature_Funnel_plate": 24.5,
          "mixer_torque_M1": 0.038,
          "mixer_torque_M2": 0.151
     },
     "4": {
          "Time": "09:51:35.359",
          "ac_flowrate": 0.0,
          "cp_flowrate": 0.0,
          "cp_pressure": 0.001,
          "cp_temperature": 0.0,
          "mixer_motor_temperature_M1": 14.5,
          "mixer_motor_temperature_M2": 16.8,
          "mixer_pressure": 0.142,
          "mixer_speed_M1": 0.0,
          "mixer_speed_M2": 0.0,
          "mixer_temperature_Funnel": 24.6,
          "mixer_temperature_Funnel_outlet": 25.1,
          "mixer_temperature_Funnel_plate": 24.5,
          "mixer_torque_M1": 0.076,
          "mixer_torque_M2": 0.151
     },
     "5": {
          "Time": "09:51:36.463",
          "ac_flowrate": 0.0,
          "cp_flowrate": 0.0,
          "cp_pressure": 0.011,
          "cp_temperature": 0.0,
          "mixer_motor_temperature_M1": 15.0,
          "mixer_motor_temperature_M2": 16.6,
          "mixer_pressure": 0.208,
          "mixer_speed_M1": 0.0,
          "mixer_speed_M2": 0.0,
          "mixer_temperature_Funnel": 24.6,
          "mixer_temperature_Funnel_outlet": 25.1,
          "mixer_temperature_Funnel_plate": 24.5,
          "mixer_torque_M1": 0.189,
          "mixer_torque_M2": 0.113
     },
     "6": {
          "Time": "09:51:37.568",
          "ac_flowrate": 0.0,
          "cp_flowrate": 0.0,
          "cp_pressure": 0.0,
          "cp_temperature": 0.0,
          "mixer_motor_temperature_M1": 14.8,
          "mixer_motor_temperature_M2": 16.1,
          "mixer_pressure": 0.261,
          "mixer_speed_M1": 0.0,
          "mixer_speed_M2": 0.0,
          "mixer_temperature_Funnel": 24.5,
          "mixer_temperature_Funnel_outlet": 25.1,
          "mixer_temperature_Funnel_plate": 24.5,
          "mixer_torque_M1": 0.113,
          "mixer_torque_M2": 0.189
     },
     "7": {
          "Time": "09:51:38.678",
          "ac_flowrate": 0.0,
          "cp_flowrate": 0.0,
          "cp_pressure": 0.084,
          "cp_temperature": 0.0,
          "mixer_motor_temperature_M1": 13.6,
          "mixer_motor_temperature_M2": 16.8,
          "mixer_pressure": 0.204,
          "mixer_speed_M1": 0.0,
          "mixer_speed_M2": 0.0,
          "mixer_temperature_Funnel": 24.6,
          "mixer_temperature_Funnel_outlet": 25.1,
          "mixer_temperature_Funnel_plate": 26.0,
          "mixer_torque_M1": 0.038,
          "mixer_torque_M2": 0.076
     },
     "8": {
          "Time": "09:51:39.788",
          "ac_flowrate": 0.0,
          "cp_flowrate": 0.0,
          "cp_pressure": 0.052,
          "cp_temperature": 0.0,
          "mixer_motor_temperature_M1": 14.8,
          "mixer_motor_temperature_M2": 16.3,
          "mixer_pressure": 0.173,
          "mixer_speed_M1": 0.0,
          "mixer_speed_M2": 0.0,
          "mixer_temperature_Funnel": 24.6,
          "mixer_temperature_Funnel_outlet": 25.1,
          "mixer_temperature_Funnel_plate": 24.5,
          "mixer_torque_M1": 0.076,
          "mixer_torque_M2": 0.189
     },
     "9": {
          "Time": "09:51:40.898",
          "ac_flowrate": 0.0,
          "cp_flowrate": 0.0,
          "cp_pressure": 0.002,
          "cp_temperature": 0.0,
          "mixer_motor_temperature_M1": 14.5,
          "mixer_motor_temperature_M2": 16.6,
          "mixer_pressure": 0.326,
          "mixer_speed_M1": 0.0,
          "mixer_speed_M2": 0.0,
          "mixer_temperature_Funnel": 24.6,
          "mixer_temperature_Funnel_outlet": 25.1,
          "mixer_temperature_Funnel_plate": 24.5,
          "mixer_torque_M1": 0.076,
          "mixer_torque_M2": 0.076
     },
     "10": {
          "Time": "09:51:42.006",
          "ac_flowrate": 0.0,
          "cp_flowrate": 0.0,
          "cp_pressure": 0.017,
          "cp_temperature": 0.0,
          "mixer_motor_temperature_M1": 14.3,
          "mixer_motor_temperature_M2": 16.1,
          "mixer_pressure": 0.184,
          "mixer_speed_M1": 0.0,
          "mixer_speed_M2": 0.0,
          "mixer_temperature_Funnel": 24.6,
          "mixer_temperature_Funnel_outlet": 27.1,
          "mixer_temperature_Funnel_plate": 24.5,
          "mixer_torque_M1": 0.113,
          "mixer_torque_M2": 0.189
     },
     "11": {
          "Time": "09:51:43.110",
          "ac_flowrate": 0.0,
          "cp_flowrate": 0.0,
          "cp_pressure": 0.005,
          "cp_temperature": 0.0,
          "mixer_motor_temperature_M1": 15.4,
          "mixer_motor_temperature_M2": 17.0,
          "mixer_pressure": 0.293,
          "mixer_speed_M1": 0.0,
          "mixer_speed_M2": 0.0,
          "mixer_temperature_Funnel": 26.0,
          "mixer_temperature_Funnel_outlet": 25.1,
          "mixer_temperature_Funnel_plate": 24.5,
          "mixer_torque_M1": 0.076,
          "mixer_torque_M2": 0.151
     }
}