{
     "1": {
          "Time": "10:44:24.821",
          "mixer_motor_temperature_M1": 12.9,
          "mixer_motor_temperature_M2": 17.5,
          "mixer_speed_M1": 21.1015,
          "mixer_speed_M2": 20.3437,
          "mixer_torque_M1": 2.2278,
          "mixer_torque_M2": 4.0026
     },
     "2": {
          "Time": "10:44:25.767",
          "mixer_motor_temperature_M1": 13.2,
          "mixer_motor_temperature_M2": 17.5,
          "mixer_speed_M1": 20.3746,
          "mixer_speed_M2": 20.2578,
          "mixer_torque_M1": 2.6054,
          "mixer_torque_M2": 3.9648
     },
     "3": {
          "Time": "10:44:26.510",
          "mixer_motor_temperature_M1": 13.2,
          "mixer_motor_temperature_M2": 17.3,
          "mixer_speed_M1": 20.3459,
          "mixer_speed_M2": 20.4246,
          "mixer_torque_M1": 2.3789,
          "mixer_torque_M2": 4.569
     },
     "4": {
          "Time": "10:44:27.268",
          "mixer_motor_temperature_M1": 13.2,
          "mixer_motor_temperature_M2": 17.7,
          "mixer_speed_M1": 20.3919,
          "mixer_speed_M2": 20.2034,
          "mixer_torque_M1": 2.1901,
          "mixer_torque_M2": 4.0026
     },
     "5": {
          "Time": "10:44:28.009",
          "mixer_motor_temperature_M1": 12.9,
          "mixer_motor_temperature_M2": 17.5,
          "mixer_speed_M1": 20.4751,
          "mixer_speed_M2": 20.545,
          "mixer_torque_M1": 2.2278,
          "mixer_torque_M2": 2.9075
     },
     "6": {
          "Time": "10:44:28.766",
          "mixer_motor_temperature_M1": 12.5,
          "mixer_motor_temperature_M2": 17.3,
          "mixer_speed_M1": 20.3473,
          "mixer_speed_M2": 20.0882,
          "mixer_torque_M1": 2.681,
          "mixer_torque_M2": 4.1536
     },
     "7": {
          "Time": "10:44:29.531",
          "mixer_motor_temperature_M1": 12.7,
          "mixer_motor_temperature_M2": 17.5,
          "mixer_speed_M1": 20.4956,
          "mixer_speed_M2": 20.4145,
          "mixer_torque_M1": 2.3411,
          "mixer_torque_M2": 3.8893
     },
     "8": {
          "Time": "10:44:30.291",
          "mixer_motor_temperature_M1": 12.7,
          "mixer_motor_temperature_M2": 17.5,
          "mixer_speed_M1": 20.4205,
          "mixer_speed_M2": 20.4319,
          "mixer_torque_M1": 2.0768,
          "mixer_torque_M2": 4.0403
     },
     "9": {
          "Time": "10:44:31.061",
          "mixer_motor_temperature_M1": 12.3,
          "mixer_motor_temperature_M2": 17.9,
          "mixer_speed_M1": 20.3348,
          "mixer_speed_M2": 20.4086,
          "mixer_torque_M1": 2.039,
          "mixer_torque_M2": 3.7382
     },
     "10": {
          "Time": "10:44:31.818",
          "mixer_motor_temperature_M1": 12.3,
          "mixer_motor_temperature_M2": 17.3,
          "mixer_speed_M1": 20.3875,
          "mixer_speed_M2": 20.2415,
          "mixer_torque_M1": 2.7565,
          "mixer_torque_M2": 3.927
     },
     "11": {
          "Time": "10:44:32.578",
          "mixer_motor_temperature_M1": 12.7,
          "mixer_motor_temperature_M2": 17.5,
          "mixer_speed_M1": 20.2873,
          "mixer_speed_M2": 20.4744,
          "mixer_torque_M1": 2.3034,
          "mixer_torque_M2": 4.0026
     },
     "12": {
          "Time": "10:44:33.340",
          "mixer_motor_temperature_M1": 13.4,
          "mixer_motor_temperature_M2": 17.0,
          "mixer_speed_M1": 20.4091,
          "mixer_speed_M2": 20.1804,
          "mixer_torque_M1": 2.3789,
          "mixer_torque_M2": 3.0963
     },
     "13": {
          "Time": "10:44:34.100",
          "mixer_motor_temperature_M1": 13.2,
          "mixer_motor_temperature_M2": 17.9,
          "mixer_speed_M1": 20.234,
          "mixer_speed_M2": 20.5516,
          "mixer_torque_M1": 2.4166,
          "mixer_torque_M2": 3.5117
     },
     "14": {
          "Time": "10:44:34.860",
          "mixer_motor_temperature_M1": 12.5,
          "mixer_motor_temperature_M2": 17.5,
          "mixer_speed_M1": 20.4398,
          "mixer_speed_M2": 20.544,
          "mixer_torque_M1": 2.832,
          "mixer_torque_M2": 3.8138
     },
     "15": {
          "Time": "10:44:35.614",
          "mixer_motor_temperature_M1": 12.9,
          "mixer_motor_temperature_M2": 17.7,
          "mixer_speed_M1": 20.3,
          "mixer_speed_M2": 20.3408,
          "mixer_torque_M1": 2.9075,
          "mixer_torque_M2": 3.6627
     },
     "16": {
          "Time": "10:44:36.374",
          "mixer_motor_temperature_M1": 12.9,
          "mixer_motor_temperature_M2": 17.5,
          "mixer_speed_M1": 20.4035,
          "mixer_speed_M2": 20.4746,
          "mixer_torque_M1": 1.8125,
          "mixer_torque_M2": 3.3606
     },
     "17": {
          "Time": "10:44:37.133",
          "mixer_motor_temperature_M1": 13.2,
          "mixer_motor_temperature_M2": 17.5,
          "mixer_speed_M1": 20.196,
          "mixer_speed_M2": 20.29,
          "mixer_torque_M1": 2.2656,
          "mixer_torque_M2": 3.4739
     },
     "18": {
          "Time": "10:44:37.892",
          "mixer_motor_temperature_M1": 13.2,
          "mixer_motor_temperature_M2": 17.5,
          "mixer_speed_M1": 20.7267,
          "mixer_speed_M2": 20.3994,
          "mixer_torque_M1": 2.5299,
          "mixer_torque_M2": 3.8138
     },
     "19": {
          "Time": "10:44:38.652",
          "mixer_motor_temperature_M1": 12.3,
          "mixer_motor_temperature_M2": 17.3,
          "mixer_speed_M1": 20.3038,
          "mixer_speed_M2": 20.4381,
          "mixer_torque_M1": 2.3789,
          "mixer_torque_M2": 4.7955
     },
     "20": {
          "Time": "10:44:39.427",
          "mixer_motor_temperature_M1": 13.2,
          "mixer_motor_temperature_M2": 17.3,
          "mixer_speed_M1": 20.3117,
          "mixer_speed_M2": 20.3488,
          "mixer_torque_M1": 2.1523,
          "mixer_torque_M2": 3.3606
     },
     "21": {
          "Time": "10:44:40.172",
          "mixer_motor_temperature_M1": 13.2,
          "mixer_motor_temperature_M2": 17.3,
          "mixer_speed_M1": 20.2557,
          "mixer_speed_M2": 20.3698,
          "mixer_torque_M1": 2.5299,
          "mixer_torque_M2": 3.3984
     },
     "22": {
          "Time": "10:44:40.934",
          "mixer_motor_temperature_M1": 13.2,
          "mixer_motor_temperature_M2": 17.0,
          "mixer_speed_M1": 20.4156,
          "mixer_speed_M2": 20.3457,
          "mixer_torque_M1": 2.3034,
          "mixer_torque_M2": 3.776
     },
     "23": {
          "Time": "10:44:41.697",
          "mixer_motor_temperature_M1": 12.7,
          "mixer_motor_temperature_M2": 17.3,
          "mixer_speed_M1": 20.2704,
          "mixer_speed_M2": 20.1227,
          "mixer_torque_M1": 2.832,
          "mixer_torque_M2": 3.2474
     },
     "24": {
          "Time": "10:44:42.459",
          "mixer_motor_temperature_M1": 13.4,
          "mixer_motor_temperature_M2": 17.3,
          "mixer_speed_M1": 20.3747,
          "mixer_speed_M2": 20.4126,
          "mixer_torque_M1": 3.0208,
          "mixer_torque_M2": 3.927
     },
     "25": {
          "Time": "10:44:43.221",
          "mixer_motor_temperature_M1": 12.9,
          "mixer_motor_temperature_M2": 17.0,
          "mixer_speed_M1": 20.2773,
          "mixer_speed_M2": 20.3866,
          "mixer_torque_M1": 2.5677,
          "mixer_torque_M2": 3.2474
     },
     "26": {
          "Time": "10:44:43.970",
          "mixer_motor_temperature_M1": 12.7,
          "mixer_motor_temperature_M2": 17.3,
          "mixer_speed_M1": 20.4908,
          "mixer_speed_M2": 20.4585,
          "mixer_torque_M1": 2.681,
          "mixer_torque_M2": 3.8515
     },
     "27": {
          "Time": "10:44:44.746",
          "mixer_motor_temperature_M1": 12.9,
          "mixer_motor_temperature_M2": 17.0,
          "mixer_speed_M1": 20.2857,
          "mixer_speed_M2": 20.4144,
          "mixer_torque_M1": 2.4166,
          "mixer_torque_M2": 3.5872
     },
     "28": {
          "Time": "10:44:45.502",
          "mixer_motor_temperature_M1": 12.3,
          "mixer_motor_temperature_M2": 17.3,
          "mixer_speed_M1": 20.3886,
          "mixer_speed_M2": 20.2927,
          "mixer_torque_M1": 2.3411,
          "mixer_torque_M2": 4.4557
     },
     "29": {
          "Time": "10:44:46.262",
          "mixer_motor_temperature_M1": 12.9,
          "mixer_motor_temperature_M2": 17.5,
          "mixer_speed_M1": 20.7496,
          "mixer_speed_M2": 20.4762,
          "mixer_torque_M1": 2.3789,
          "mixer_torque_M2": 3.927
     },
     "30": {
          "Time": "10:44:47.020",
          "mixer_motor_temperature_M1": 12.9,
          "mixer_motor_temperature_M2": 17.0,
          "mixer_speed_M1": 20.5361,
          "mixer_speed_M2": 20.374,
          "mixer_torque_M1": 2.7942,
          "mixer_torque_M2": 3.5117
     },
     "31": {
          "Time": "10:44:47.779",
          "mixer_motor_temperature_M1": 12.5,
          "mixer_motor_temperature_M2": 17.5,
          "mixer_speed_M1": 20.4309,
          "mixer_speed_M2": 20.4406,
          "mixer_torque_M1": 2.4922,
          "mixer_torque_M2": 4.3802
     },
     "32": {
          "Time": "10:44:48.539",
          "mixer_motor_temperature_M1": 12.9,
          "mixer_motor_temperature_M2": 17.7,
          "mixer_speed_M1": 20.7956,
          "mixer_speed_M2": 20.3659,
          "mixer_torque_M1": 2.6054,
          "mixer_torque_M2": 3.4362
     },
     "33": {
          "Time": "10:44:49.301",
          "mixer_motor_temperature_M1": 13.2,
          "mixer_motor_temperature_M2": 17.5,
          "mixer_speed_M1": 20.4341,
          "mixer_speed_M2": 20.4047,
          "mixer_torque_M1": 2.4922,
          "mixer_torque_M2": 3.8138
     },
     "34": {
          "Time": "10:44:50.059",
          "mixer_motor_temperature_M1": 13.6,
          "mixer_motor_temperature_M2": 17.0,
          "mixer_speed_M1": 20.3802,
          "mixer_speed_M2": 20.3736,
          "mixer_torque_M1": 2.4544,
          "mixer_torque_M2": 4.0781
     },
     "35": {
          "Time": "10:44:50.818",
          "mixer_motor_temperature_M1": 13.2,
          "mixer_motor_temperature_M2": 17.3,
          "mixer_speed_M1": 20.3618,
          "mixer_speed_M2": 20.526,
          "mixer_torque_M1": 2.4544,
          "mixer_torque_M2": 3.3229
     },
     "36": {
          "Time": "10:44:51.562",
          "mixer_motor_temperature_M1": 13.6,
          "mixer_motor_temperature_M2": 17.0,
          "mixer_speed_M1": 20.2618,
          "mixer_speed_M2": 20.0077,
          "mixer_torque_M1": 2.1901,
          "mixer_torque_M2": 3.4362
     },
     "37": {
          "Time": "10:44:52.324",
          "mixer_motor_temperature_M1": 13.6,
          "mixer_motor_temperature_M2": 17.7,
          "mixer_speed_M1": 20.5133,
          "mixer_speed_M2": 20.4487,
          "mixer_torque_M1": 2.4544,
          "mixer_torque_M2": 3.5494
     },
     "38": {
          "Time": "10:44:53.100",
          "mixer_motor_temperature_M1": 12.7,
          "mixer_motor_temperature_M2": 17.5,
          "mixer_speed_M1": 20.4177,
          "mixer_speed_M2": 20.4972,
          "mixer_torque_M1": 2.4544,
          "mixer_torque_M2": 3.2096
     },
     "39": {
          "Time": "10:44:53.862",
          "mixer_motor_temperature_M1": 12.5,
          "mixer_motor_temperature_M2": 17.0,
          "mixer_speed_M1": 20.2255,
          "mixer_speed_M2": 20.2752,
          "mixer_torque_M1": 2.2278,
          "mixer_torque_M2": 3.927
     },
     "40": {
          "Time": "10:44:54.614",
          "mixer_motor_temperature_M1": 13.8,
          "mixer_motor_temperature_M2": 17.0,
          "mixer_speed_M1": 20.4037,
          "mixer_speed_M2": 20.4367,
          "mixer_torque_M1": 2.039,
          "mixer_torque_M2": 3.3984
     },
     "41": {
          "Time": "10:44:55.375",
          "mixer_motor_temperature_M1": 12.9,
          "mixer_motor_temperature_M2": 17.0,
          "mixer_speed_M1": 20.4964,
          "mixer_speed_M2": 20.3112,
          "mixer_torque_M1": 2.9453,
          "mixer_torque_M2": 3.9648
     },
     "42": {
          "Time": "10:44:56.139",
          "mixer_motor_temperature_M1": 12.7,
          "mixer_motor_temperature_M2": 16.8,
          "mixer_speed_M1": 20.4697,
          "mixer_speed_M2": 20.4944,
          "mixer_torque_M1": 2.3034,
          "mixer_torque_M2": 3.2851
     },
     "43": {
          "Time": "10:44:56.898",
          "mixer_motor_temperature_M1": 12.7,
          "mixer_motor_temperature_M2": 17.3,
          "mixer_speed_M1": 20.3518,
          "mixer_speed_M2": 20.3064,
          "mixer_torque_M1": 2.1146,
          "mixer_torque_M2": 3.776
     },
     "44": {
          "Time": "10:44:57.654",
          "mixer_motor_temperature_M1": 13.2,
          "mixer_motor_temperature_M2": 17.0,
          "mixer_speed_M1": 20.387,
          "mixer_speed_M2": 20.5572,
          "mixer_torque_M1": 2.2278,
          "mixer_torque_M2": 2.7942
     },
     "45": {
          "Time": "10:44:58.427",
          "mixer_motor_temperature_M1": 13.4,
          "mixer_motor_temperature_M2": 17.3,
          "mixer_speed_M1": 20.3312,
          "mixer_speed_M2": 20.3661,
          "mixer_torque_M1": 2.6054,
          "mixer_torque_M2": 3.3229
     },
     "46": {
          "Time": "10:44:59.191",
          "mixer_motor_temperature_M1": 12.7,
          "mixer_motor_temperature_M2": 17.5,
          "mixer_speed_M1": 20.2295,
          "mixer_speed_M2": 20.3244,
          "mixer_torque_M1": 2.2656,
          "mixer_torque_M2": 3.7382
     },
     "47": {
          "Time": "10:44:59.952",
          "mixer_motor_temperature_M1": 13.2,
          "mixer_motor_temperature_M2": 17.0,
          "mixer_speed_M1": 39.6507,
          "mixer_speed_M2": 39.4142,
          "mixer_torque_M1": 3.3984,
          "mixer_torque_M2": 4.0781
     },
     "48": {
          "Time": "10:45:00.713",
          "mixer_motor_temperature_M1": 13.4,
          "mixer_motor_temperature_M2": 17.3,
          "mixer_speed_M1": 39.5215,
          "mixer_speed_M2": 39.6735,
          "mixer_torque_M1": 3.1718,
          "mixer_torque_M2": 4.72
     },
     "49": {
          "Time": "10:45:01.469",
          "mixer_motor_temperature_M1": 12.9,
          "mixer_motor_temperature_M2": 17.5,
          "mixer_speed_M1": 39.5866,
          "mixer_speed_M2": 39.5882,
          "mixer_torque_M1": 3.0586,
          "mixer_torque_M2": 3.927
     },
     "50": {
          "Time": "10:45:02.233",
          "mixer_motor_temperature_M1": 13.2,
          "mixer_motor_temperature_M2": 17.3,
          "mixer_speed_M1": 39.589,
          "mixer_speed_M2": 39.5568,
          "mixer_torque_M1": 3.6627,
          "mixer_torque_M2": 4.7955
     },
     "51": {
          "Time": "10:45:02.977",
          "mixer_motor_temperature_M1": 12.7,
          "mixer_motor_temperature_M2": 17.5,
          "mixer_speed_M1": 39.749,
          "mixer_speed_M2": 39.5134,
          "mixer_torque_M1": 3.0208,
          "mixer_torque_M2": 4.1536
     },
     "52": {
          "Time": "10:45:03.738",
          "mixer_motor_temperature_M1": 12.5,
          "mixer_motor_temperature_M2": 17.0,
          "mixer_speed_M1": 39.6723,
          "mixer_speed_M2": 39.5134,
          "mixer_torque_M1": 3.4362,
          "mixer_torque_M2": 4.4557
     },
     "53": {
          "Time": "10:45:04.499",
          "mixer_motor_temperature_M1": 12.7,
          "mixer_motor_temperature_M2": 17.3,
          "mixer_speed_M1": 39.6279,
          "mixer_speed_M2": 39.4933,
          "mixer_torque_M1": 3.5494,
          "mixer_torque_M2": 3.7382
     },
     "54": {
          "Time": "10:45:05.260",
          "mixer_motor_temperature_M1": 13.2,
          "mixer_motor_temperature_M2": 17.3,
          "mixer_speed_M1": 39.6193,
          "mixer_speed_M2": 39.4422,
          "mixer_torque_M1": 2.983,
          "mixer_torque_M2": 4.871
     },
     "55": {
          "Time": "10:45:06.032",
          "mixer_motor_temperature_M1": 13.2,
          "mixer_motor_temperature_M2": 17.0,
          "mixer_speed_M1": 39.5626,
          "mixer_speed_M2": 39.6336,
          "mixer_torque_M1": 2.9453,
          "mixer_torque_M2": 3.776
     },
     "56": {
          "Time": "10:45:06.791",
          "mixer_motor_temperature_M1": 12.7,
          "mixer_motor_temperature_M2": 17.7,
          "mixer_speed_M1": 39.5599,
          "mixer_speed_M2": 39.6161,
          "mixer_torque_M1": 3.1718,
          "mixer_torque_M2": 4.7955
     },
     "57": {
          "Time": "10:45:07.553",
          "mixer_motor_temperature_M1": 12.7,
          "mixer_motor_temperature_M2": 17.0,
          "mixer_speed_M1": 39.6597,
          "mixer_speed_M2": 39.5675,
          "mixer_torque_M1": 3.2096,
          "mixer_torque_M2": 4.5312
     },
     "58": {
          "Time": "10:45:08.316",
          "mixer_motor_temperature_M1": 12.3,
          "mixer_motor_temperature_M2": 17.5,
          "mixer_speed_M1": 39.4427,
          "mixer_speed_M2": 39.5533,
          "mixer_torque_M1": 3.3606,
          "mixer_torque_M2": 5.0221
     },
     "59": {
          "Time": "10:45:09.076",
          "mixer_motor_temperature_M1": 12.9,
          "mixer_motor_temperature_M2": 17.3,
          "mixer_speed_M1": 39.5838,
          "mixer_speed_M2": 39.4534,
          "mixer_torque_M1": 3.2474,
          "mixer_torque_M2": 3.6627
     },
     "60": {
          "Time": "10:45:09.867",
          "mixer_motor_temperature_M1": 13.2,
          "mixer_motor_temperature_M2": 17.0,
          "mixer_speed_M1": 39.6772,
          "mixer_speed_M2": 39.7678,
          "mixer_torque_M1": 3.2474,
          "mixer_torque_M2": 5.1354
     },
     "61": {
          "Time": "10:45:10.625",
          "mixer_motor_temperature_M1": 13.2,
          "mixer_motor_temperature_M2": 16.8,
          "mixer_speed_M1": 39.6286,
          "mixer_speed_M2": 39.628,
          "mixer_torque_M1": 4.1158,
          "mixer_torque_M2": 4.0403
     },
     "62": {
          "Time": "10:45:11.382",
          "mixer_motor_temperature_M1": 13.6,
          "mixer_motor_temperature_M2": 17.3,
          "mixer_speed_M1": 39.4968,
          "mixer_speed_M2": 39.5849,
          "mixer_torque_M1": 2.8698,
          "mixer_torque_M2": 4.3424
     },
     "63": {
          "Time": "10:45:12.135",
          "mixer_motor_temperature_M1": 12.9,
          "mixer_motor_temperature_M2": 17.3,
          "mixer_speed_M1": 39.4567,
          "mixer_speed_M2": 39.568,
          "mixer_torque_M1": 3.2851,
          "mixer_torque_M2": 5.3619
     },
     "64": {
          "Time": "10:45:12.888",
          "mixer_motor_temperature_M1": 13.2,
          "mixer_motor_temperature_M2": 17.3,
          "mixer_speed_M1": 39.7257,
          "mixer_speed_M2": 39.9936,
          "mixer_torque_M1": 3.0586,
          "mixer_torque_M2": 6.2682
     },
     "65": {
          "Time": "10:45:13.651",
          "mixer_motor_temperature_M1": 12.7,
          "mixer_motor_temperature_M2": 17.0,
          "mixer_speed_M1": 39.4997,
          "mixer_speed_M2": 39.4259,
          "mixer_torque_M1": 3.1341,
          "mixer_torque_M2": 4.2291
     },
     "66": {
          "Time": "10:45:14.412",
          "mixer_motor_temperature_M1": 12.7,
          "mixer_motor_temperature_M2": 17.0,
          "mixer_speed_M1": 39.3398,
          "mixer_speed_M2": 39.926,
          "mixer_torque_M1": 3.2096,
          "mixer_torque_M2": 5.0221
     },
     "67": {
          "Time": "10:45:15.154",
          "mixer_motor_temperature_M1": 12.7,
          "mixer_motor_temperature_M2": 17.0,
          "mixer_speed_M1": 60.1627,
          "mixer_speed_M2": 59.9628,
          "mixer_torque_M1": 4.569,
          "mixer_torque_M2": 6.3059
     },
     "68": {
          "Time": "10:45:15.902",
          "mixer_motor_temperature_M1": 12.7,
          "mixer_motor_temperature_M2": 17.0,
          "mixer_speed_M1": 59.9312,
          "mixer_speed_M2": 59.8769,
          "mixer_torque_M1": 3.776,
          "mixer_torque_M2": 5.0976
     },
     "69": {
          "Time": "10:45:16.656",
          "mixer_motor_temperature_M1": 13.2,
          "mixer_motor_temperature_M2": 17.3,
          "mixer_speed_M1": 60.1411,
          "mixer_speed_M2": 59.7076,
          "mixer_torque_M1": 4.9843,
          "mixer_torque_M2": 5.7018
     },
     "70": {
          "Time": "10:45:17.416",
          "mixer_motor_temperature_M1": 12.7,
          "mixer_motor_temperature_M2": 17.5,
          "mixer_speed_M1": 60.2288,
          "mixer_speed_M2": 59.8402,
          "mixer_torque_M1": 4.2669,
          "mixer_torque_M2": 5.9283
     },
     "71": {
          "Time": "10:45:18.193",
          "mixer_motor_temperature_M1": 12.7,
          "mixer_motor_temperature_M2": 17.0,
          "mixer_speed_M1": 60.8657,
          "mixer_speed_M2": 59.6771,
          "mixer_torque_M1": 3.8893,
          "mixer_torque_M2": 5.7018
     },
     "72": {
          "Time": "10:45:18.967",
          "mixer_motor_temperature_M1": 13.2,
          "mixer_motor_temperature_M2": 17.3,
          "mixer_speed_M1": 60.009,
          "mixer_speed_M2": 59.7913,
          "mixer_torque_M1": 3.9648,
          "mixer_torque_M2": 4.4934
     },
     "73": {
          "Time": "10:45:19.725",
          "mixer_motor_temperature_M1": 12.5,
          "mixer_motor_temperature_M2": 17.3,
          "mixer_speed_M1": 60.3112,
          "mixer_speed_M2": 60.1691,
          "mixer_torque_M1": 3.4739,
          "mixer_torque_M2": 5.664
     },
     "74": {
          "Time": "10:45:20.483",
          "mixer_motor_temperature_M1": 12.7,
          "mixer_motor_temperature_M2": 17.3,
          "mixer_speed_M1": 60.2582,
          "mixer_speed_M2": 60.0775,
          "mixer_torque_M1": 4.7578,
          "mixer_torque_M2": 5.8528
     },
     "75": {
          "Time": "10:45:21.246",
          "mixer_motor_temperature_M1": 13.4,
          "mixer_motor_temperature_M2": 17.5,
          "mixer_speed_M1": 59.9416,
          "mixer_speed_M2": 59.9367,
          "mixer_torque_M1": 5.1731,
          "mixer_torque_M2": 6.0794
     },
     "76": {
          "Time": "10:45:22.001",
          "mixer_motor_temperature_M1": 12.5,
          "mixer_motor_temperature_M2": 17.3,
          "mixer_speed_M1": 59.848,
          "mixer_speed_M2": 60.1278,
          "mixer_torque_M1": 4.5312,
          "mixer_torque_M2": 4.9843
     },
     "77": {
          "Time": "10:45:22.759",
          "mixer_motor_temperature_M1": 13.6,
          "mixer_motor_temperature_M2": 17.0,
          "mixer_speed_M1": 59.8769,
          "mixer_speed_M2": 60.1714,
          "mixer_torque_M1": 3.7005,
          "mixer_torque_M2": 5.9283
     },
     "78": {
          "Time": "10:45:23.521",
          "mixer_motor_temperature_M1": 13.6,
          "mixer_motor_temperature_M2": 17.5,
          "mixer_speed_M1": 60.0331,
          "mixer_speed_M2": 60.0164,
          "mixer_torque_M1": 4.3424,
          "mixer_torque_M2": 5.8528
     },
     "79": {
          "Time": "10:45:24.285",
          "mixer_motor_temperature_M1": 13.2,
          "mixer_motor_temperature_M2": 17.3,
          "mixer_speed_M1": 59.7429,
          "mixer_speed_M2": 60.2194,
          "mixer_torque_M1": 4.2669,
          "mixer_torque_M2": 6.0038
     },
     "80": {
          "Time": "10:45:25.042",
          "mixer_motor_temperature_M1": 13.4,
          "mixer_motor_temperature_M2": 17.3,
          "mixer_speed_M1": 59.8727,
          "mixer_speed_M2": 59.9668,
          "mixer_torque_M1": 4.0403,
          "mixer_torque_M2": 5.4752
     },
     "81": {
          "Time": "10:45:25.803",
          "mixer_motor_temperature_M1": 12.7,
          "mixer_motor_temperature_M2": 17.5,
          "mixer_speed_M1": 60.2201,
          "mixer_speed_M2": 60.3772,
          "mixer_torque_M1": 3.1718,
          "mixer_torque_M2": 5.3997
     },
     "82": {
          "Time": "10:45:26.562",
          "mixer_motor_temperature_M1": 13.2,
          "mixer_motor_temperature_M2": 17.3,
          "mixer_speed_M1": 60.0931,
          "mixer_speed_M2": 60.1127,
          "mixer_torque_M1": 4.1158,
          "mixer_torque_M2": 5.2864
     },
     "83": {
          "Time": "10:45:27.334",
          "mixer_motor_temperature_M1": 13.6,
          "mixer_motor_temperature_M2": 17.5,
          "mixer_speed_M1": 59.9468,
          "mixer_speed_M2": 60.0941,
          "mixer_torque_M1": 4.4179,
          "mixer_torque_M2": 5.815
     },
     "84": {
          "Time": "10:45:28.096",
          "mixer_motor_temperature_M1": 12.5,
          "mixer_motor_temperature_M2": 17.0,
          "mixer_speed_M1": 59.8604,
          "mixer_speed_M2": 60.4069,
          "mixer_torque_M1": 4.0781,
          "mixer_torque_M2": 5.9283
     },
     "85": {
          "Time": "10:45:28.858",
          "mixer_motor_temperature_M1": 14.1,
          "mixer_motor_temperature_M2": 17.7,
          "mixer_speed_M1": 60.2039,
          "mixer_speed_M2": 59.9302,
          "mixer_torque_M1": 4.0403,
          "mixer_torque_M2": 4.9466
     },
     "86": {
          "Time": "10:45:29.615",
          "mixer_motor_temperature_M1": 12.3,
          "mixer_motor_temperature_M2": 17.5,
          "mixer_speed_M1": 60.0443,
          "mixer_speed_M2": 60.1252,
          "mixer_torque_M1": 5.2486,
          "mixer_torque_M2": 7.0234
     },
     "87": {
          "Time": "10:45:30.379",
          "mixer_motor_temperature_M1": 13.8,
          "mixer_motor_temperature_M2": 17.5,
          "mixer_speed_M1": 80.7804,
          "mixer_speed_M2": 80.3389,
          "mixer_torque_M1": 5.1354,
          "mixer_torque_M2": 7.0611
     },
     "88": {
          "Time": "10:45:31.157",
          "mixer_motor_temperature_M1": 12.7,
          "mixer_motor_temperature_M2": 17.5,
          "mixer_speed_M1": 80.4886,
          "mixer_speed_M2": 80.1387,
          "mixer_torque_M1": 4.7578,
          "mixer_torque_M2": 6.0416
     },
     "89": {
          "Time": "10:45:31.920",
          "mixer_motor_temperature_M1": 12.9,
          "mixer_motor_temperature_M2": 17.5,
          "mixer_speed_M1": 80.5923,
          "mixer_speed_M2": 80.5221,
          "mixer_torque_M1": 4.2669,
          "mixer_torque_M2": 7.2499
     },
     "90": {
          "Time": "10:45:32.681",
          "mixer_motor_temperature_M1": 13.2,
          "mixer_motor_temperature_M2": 17.5,
          "mixer_speed_M1": 80.4601,
          "mixer_speed_M2": 80.3248,
          "mixer_torque_M1": 4.0403,
          "mixer_torque_M2": 6.3437
     },
     "91": {
          "Time": "10:45:33.443",
          "mixer_motor_temperature_M1": 12.7,
          "mixer_motor_temperature_M2": 17.7,
          "mixer_speed_M1": 80.0346,
          "mixer_speed_M2": 80.2648,
          "mixer_torque_M1": 4.0403,
          "mixer_torque_M2": 6.9101
     },
     "92": {
          "Time": "10:45:34.202",
          "mixer_motor_temperature_M1": 12.7,
          "mixer_motor_temperature_M2": 17.3,
          "mixer_speed_M1": 80.3423,
          "mixer_speed_M2": 80.2411,
          "mixer_torque_M1": 4.0403,
          "mixer_torque_M2": 6.5702
     },
     "93": {
          "Time": "10:45:34.975",
          "mixer_motor_temperature_M1": 12.9,
          "mixer_motor_temperature_M2": 17.9,
          "mixer_speed_M1": 80.5884,
          "mixer_speed_M2": 81.3242,
          "mixer_torque_M1": 4.2669,
          "mixer_torque_M2": 6.457
     },
     "94": {
          "Time": "10:45:35.738",
          "mixer_motor_temperature_M1": 12.9,
          "mixer_motor_temperature_M2": 17.5,
          "mixer_speed_M1": 80.1662,
          "mixer_speed_M2": 81.6004,
          "mixer_torque_M1": 4.4179,
          "mixer_torque_M2": 5.8906
     },
     "95": {
          "Time": "10:45:36.501",
          "mixer_motor_temperature_M1": 12.7,
          "mixer_motor_temperature_M2": 17.7,
          "mixer_speed_M1": 79.7028,
          "mixer_speed_M2": 80.6278,
          "mixer_torque_M1": 4.0781,
          "mixer_torque_M2": 5.7773
     },
     "96": {
          "Time": "10:45:37.250",
          "mixer_motor_temperature_M1": 13.2,
          "mixer_motor_temperature_M2": 17.5,
          "mixer_speed_M1": 81.2046,
          "mixer_speed_M2": 80.5981,
          "mixer_torque_M1": 3.776,
          "mixer_torque_M2": 5.2109
     },
     "97": {
          "Time": "10:45:38.012",
          "mixer_motor_temperature_M1": 12.9,
          "mixer_motor_temperature_M2": 17.7,
          "mixer_speed_M1": 80.1487,
          "mixer_speed_M2": 80.5154,
          "mixer_torque_M1": 4.871,
          "mixer_torque_M2": 5.5507
     },
     "98": {
          "Time": "10:45:38.760",
          "mixer_motor_temperature_M1": 13.2,
          "mixer_motor_temperature_M2": 18.2,
          "mixer_speed_M1": 80.4949,
          "mixer_speed_M2": 80.5396,
          "mixer_torque_M1": 4.9466,
          "mixer_torque_M2": 5.0221
     },
     "99": {
          "Time": "10:45:39.521",
          "mixer_motor_temperature_M1": 13.2,
          "mixer_motor_temperature_M2": 17.5,
          "mixer_speed_M1": 80.3555,
          "mixer_speed_M2": 80.1031,
          "mixer_torque_M1": 4.6067,
          "mixer_torque_M2": 4.8333
     },
     "100": {
          "Time": "10:45:40.284",
          "mixer_motor_temperature_M1": 13.8,
          "mixer_motor_temperature_M2": 17.5,
          "mixer_speed_M1": 80.4875,
          "mixer_speed_M2": 80.3841,
          "mixer_torque_M1": 4.9843,
          "mixer_torque_M2": 5.4374
     },
     "101": {
          "Time": "10:45:41.049",
          "mixer_motor_temperature_M1": 13.6,
          "mixer_motor_temperature_M2": 17.5,
          "mixer_speed_M1": 80.6899,
          "mixer_speed_M2": 80.0059,
          "mixer_torque_M1": 5.2864,
          "mixer_torque_M2": 5.3242
     },
     "102": {
          "Time": "10:45:41.817",
          "mixer_motor_temperature_M1": 13.4,
          "mixer_motor_temperature_M2": 17.5,
          "mixer_speed_M1": 80.7249,
          "mixer_speed_M2": 79.9728,
          "mixer_torque_M1": 4.4179,
          "mixer_torque_M2": 5.815
     },
     "103": {
          "Time": "10:45:42.580",
          "mixer_motor_temperature_M1": 13.2,
          "mixer_motor_temperature_M2": 17.5,
          "mixer_speed_M1": 80.3278,
          "mixer_speed_M2": 79.849,
          "mixer_torque_M1": 4.6445,
          "mixer_torque_M2": 5.8906
     },
     "104": {
          "Time": "10:45:43.343",
          "mixer_motor_temperature_M1": 12.7,
          "mixer_motor_temperature_M2": 17.5,
          "mixer_speed_M1": 80.7355,
          "mixer_speed_M2": 80.2288,
          "mixer_torque_M1": 4.4934,
          "mixer_torque_M2": 6.6835
     },
     "105": {
          "Time": "10:45:44.108",
          "mixer_motor_temperature_M1": 13.2,
          "mixer_motor_temperature_M2": 17.5,
          "mixer_speed_M1": 80.5806,
          "mixer_speed_M2": 79.939,
          "mixer_torque_M1": 4.4557,
          "mixer_torque_M2": 7.401
     },
     "106": {
          "Time": "10:45:44.869",
          "mixer_motor_temperature_M1": 13.2,
          "mixer_motor_temperature_M2": 17.7,
          "mixer_speed_M1": 98.9401,
          "mixer_speed_M2": 99.0237,
          "mixer_torque_M1": 6.3059,
          "mixer_torque_M2": 7.3254
     },
     "107": {
          "Time": "10:45:45.630",
          "mixer_motor_temperature_M1": 13.2,
          "mixer_motor_temperature_M2": 18.2,
          "mixer_speed_M1": 99.7161,
          "mixer_speed_M2": 99.5649,
          "mixer_torque_M1": 6.1171,
          "mixer_torque_M2": 7.8918
     },
     "108": {
          "Time": "10:45:46.391",
          "mixer_motor_temperature_M1": 13.2,
          "mixer_motor_temperature_M2": 18.2,
          "mixer_speed_M1": 99.5602,
          "mixer_speed_M2": 99.4706,
          "mixer_torque_M1": 5.2486,
          "mixer_torque_M2": 7.1744
     },
     "109": {
          "Time": "10:45:47.152",
          "mixer_motor_temperature_M1": 13.6,
          "mixer_motor_temperature_M2": 18.2,
          "mixer_speed_M1": 99.6208,
          "mixer_speed_M2": 99.6856,
          "mixer_torque_M1": 5.6262,
          "mixer_torque_M2": 5.2486
     },
     "110": {
          "Time": "10:45:47.913",
          "mixer_motor_temperature_M1": 13.4,
          "mixer_motor_temperature_M2": 17.5,
          "mixer_speed_M1": 98.9839,
          "mixer_speed_M2": 99.9622,
          "mixer_torque_M1": 6.3059,
          "mixer_torque_M2": 7.5898
     },
     "111": {
          "Time": "10:45:48.672",
          "mixer_motor_temperature_M1": 12.9,
          "mixer_motor_temperature_M2": 18.2,
          "mixer_speed_M1": 99.3066,
          "mixer_speed_M2": 99.6453,
          "mixer_torque_M1": 5.7773,
          "mixer_torque_M2": 7.9296
     },
     "112": {
          "Time": "10:45:49.431",
          "mixer_motor_temperature_M1": 12.7,
          "mixer_motor_temperature_M2": 17.5,
          "mixer_speed_M1": 99.9243,
          "mixer_speed_M2": 99.4609,
          "mixer_torque_M1": 4.4934,
          "mixer_torque_M2": 7.4765
     },
     "113": {
          "Time": "10:45:50.195",
          "mixer_motor_temperature_M1": 13.4,
          "mixer_motor_temperature_M2": 18.2,
          "mixer_speed_M1": 100.4263,
          "mixer_speed_M2": 98.8119,
          "mixer_torque_M1": 6.0038,
          "mixer_torque_M2": 7.2122
     },
     "114": {
          "Time": "10:45:50.956",
          "mixer_motor_temperature_M1": 14.5,
          "mixer_motor_temperature_M2": 17.9,
          "mixer_speed_M1": 98.8154,
          "mixer_speed_M2": 99.7635,
          "mixer_torque_M1": 6.2682,
          "mixer_torque_M2": 8.0051
     },
     "115": {
          "Time": "10:45:51.713",
          "mixer_motor_temperature_M1": 13.4,
          "mixer_motor_temperature_M2": 17.9,
          "mixer_speed_M1": 99.8391,
          "mixer_speed_M2": 99.0292,
          "mixer_torque_M1": 5.815,
          "mixer_torque_M2": 7.7786
     },
     "116": {
          "Time": "10:45:52.469",
          "mixer_motor_temperature_M1": 13.8,
          "mixer_motor_temperature_M2": 17.7,
          "mixer_speed_M1": 100.357,
          "mixer_speed_M2": 99.2672,
          "mixer_torque_M1": 4.3424,
          "mixer_torque_M2": 7.0989
     },
     "117": {
          "Time": "10:45:53.244",
          "mixer_motor_temperature_M1": 13.6,
          "mixer_motor_temperature_M2": 17.9,
          "mixer_speed_M1": 100.1864,
          "mixer_speed_M2": 98.3619,
          "mixer_torque_M1": 5.815,
          "mixer_torque_M2": 7.9674
     },
     "118": {
          "Time": "10:45:54.002",
          "mixer_motor_temperature_M1": 12.9,
          "mixer_motor_temperature_M2": 18.2,
          "mixer_speed_M1": 99.7391,
          "mixer_speed_M2": 99.374,
          "mixer_torque_M1": 6.2682,
          "mixer_torque_M2": 7.2499
     },
     "119": {
          "Time": "10:45:54.765",
          "mixer_motor_temperature_M1": 13.2,
          "mixer_motor_temperature_M2": 17.9,
          "mixer_speed_M1": 99.6103,
          "mixer_speed_M2": 99.8252,
          "mixer_torque_M1": 5.513,
          "mixer_torque_M2": 7.9296
     },
     "120": {
          "Time": "10:45:55.531",
          "mixer_motor_temperature_M1": 13.2,
          "mixer_motor_temperature_M2": 17.9,
          "mixer_speed_M1": 99.5677,
          "mixer_speed_M2": 100.2031,
          "mixer_torque_M1": 4.4557,
          "mixer_torque_M2": 6.1171
     },
     "121": {
          "Time": "10:45:56.293",
          "mixer_motor_temperature_M1": 13.6,
          "mixer_motor_temperature_M2": 17.7,
          "mixer_speed_M1": 99.1871,
          "mixer_speed_M2": 99.785,
          "mixer_torque_M1": 5.9661,
          "mixer_torque_M2": 7.2877
     },
     "122": {
          "Time": "10:45:57.056",
          "mixer_motor_temperature_M1": 13.6,
          "mixer_motor_temperature_M2": 17.7,
          "mixer_speed_M1": 99.5434,
          "mixer_speed_M2": 99.7027,
          "mixer_torque_M1": 6.2304,
          "mixer_torque_M2": 7.3254
     },
     "123": {
          "Time": "10:45:57.816",
          "mixer_motor_temperature_M1": 14.1,
          "mixer_motor_temperature_M2": 17.9,
          "mixer_speed_M1": 99.6669,
          "mixer_speed_M2": 100.0107,
          "mixer_torque_M1": 5.7018,
          "mixer_torque_M2": 6.9856
     },
     "124": {
          "Time": "10:45:58.571",
          "mixer_motor_temperature_M1": 13.4,
          "mixer_motor_temperature_M2": 18.6,
          "mixer_speed_M1": 99.2215,
          "mixer_speed_M2": 99.9564,
          "mixer_torque_M1": 4.8333,
          "mixer_torque_M2": 5.6262
     },
     "125": {
          "Time": "10:45:59.330",
          "mixer_motor_temperature_M1": 13.4,
          "mixer_motor_temperature_M2": 18.2,
          "mixer_speed_M1": 98.8819,
          "mixer_speed_M2": 99.9074,
          "mixer_torque_M1": 6.7213,
          "mixer_torque_M2": 7.2877
     },
     "126": {
          "Time": "10:46:00.106",
          "mixer_motor_temperature_M1": 13.8,
          "mixer_motor_temperature_M2": 17.9,
          "mixer_speed_M1": 120.229,
          "mixer_speed_M2": 120.3175,
          "mixer_torque_M1": 6.608,
          "mixer_torque_M2": 7.8163
     },
     "127": {
          "Time": "10:46:00.878",
          "mixer_motor_temperature_M1": 13.2,
          "mixer_motor_temperature_M2": 17.9,
          "mixer_speed_M1": 119.8397,
          "mixer_speed_M2": 120.3886,
          "mixer_torque_M1": 6.608,
          "mixer_torque_M2": 7.8541
     },
     "128": {
          "Time": "10:46:01.641",
          "mixer_motor_temperature_M1": 13.6,
          "mixer_motor_temperature_M2": 18.2,
          "mixer_speed_M1": 120.2744,
          "mixer_speed_M2": 120.3045,
          "mixer_torque_M1": 5.815,
          "mixer_torque_M2": 8.4205
     },
     "129": {
          "Time": "10:46:02.402",
          "mixer_motor_temperature_M1": 14.1,
          "mixer_motor_temperature_M2": 18.2,
          "mixer_speed_M1": 119.8803,
          "mixer_speed_M2": 120.4204,
          "mixer_torque_M1": 6.8346,
          "mixer_torque_M2": 7.8163
     },
     "130": {
          "Time": "10:46:03.148",
          "mixer_motor_temperature_M1": 13.8,
          "mixer_motor_temperature_M2": 18.2,
          "mixer_speed_M1": 119.9197,
          "mixer_speed_M2": 120.4632,
          "mixer_torque_M1": 5.8906,
          "mixer_torque_M2": 8.4582
     },
     "131": {
          "Time": "10:46:03.907",
          "mixer_motor_temperature_M1": 13.6,
          "mixer_motor_temperature_M2": 18.2,
          "mixer_speed_M1": 118.9975,
          "mixer_speed_M2": 120.4907,
          "mixer_torque_M1": 7.5142,
          "mixer_torque_M2": 8.7603
     },
     "132": {
          "Time": "10:46:04.674",
          "mixer_motor_temperature_M1": 13.2,
          "mixer_motor_temperature_M2": 18.4,
          "mixer_speed_M1": 120.0474,
          "mixer_speed_M2": 120.1876,
          "mixer_torque_M1": 4.6822,
          "mixer_torque_M2": 8.1562
     },
     "133": {
          "Time": "10:46:05.432",
          "mixer_motor_temperature_M1": 13.2,
          "mixer_motor_temperature_M2": 17.7,
          "mixer_speed_M1": 119.1235,
          "mixer_speed_M2": 120.2294,
          "mixer_torque_M1": 6.6458,
          "mixer_torque_M2": 8.496
     },
     "134": {
          "Time": "10:46:06.190",
          "mixer_motor_temperature_M1": 13.4,
          "mixer_motor_temperature_M2": 17.9,
          "mixer_speed_M1": 120.3808,
          "mixer_speed_M2": 119.709,
          "mixer_torque_M1": 4.72,
          "mixer_torque_M2": 6.3059
     },
     "135": {
          "Time": "10:46:06.967",
          "mixer_motor_temperature_M1": 13.6,
          "mixer_motor_temperature_M2": 17.9,
          "mixer_speed_M1": 120.0046,
          "mixer_speed_M2": 119.7205,
          "mixer_torque_M1": 7.2877,
          "mixer_torque_M2": 8.2317
     },
     "136": {
          "Time": "10:46:07.729",
          "mixer_motor_temperature_M1": 13.6,
          "mixer_motor_temperature_M2": 17.9,
          "mixer_speed_M1": 120.5792,
          "mixer_speed_M2": 120.22,
          "mixer_torque_M1": 5.9283,
          "mixer_torque_M2": 6.5325
     },
     "137": {
          "Time": "10:46:08.490",
          "mixer_motor_temperature_M1": 12.7,
          "mixer_motor_temperature_M2": 18.6,
          "mixer_speed_M1": 120.5214,
          "mixer_speed_M2": 120.0155,
          "mixer_torque_M1": 6.7213,
          "mixer_torque_M2": 8.5715
     },
     "138": {
          "Time": "10:46:09.232",
          "mixer_motor_temperature_M1": 14.1,
          "mixer_motor_temperature_M2": 18.2,
          "mixer_speed_M1": 120.9265,
          "mixer_speed_M2": 120.2947,
          "mixer_torque_M1": 5.8906,
          "mixer_torque_M2": 7.3254
     },
     "139": {
          "Time": "10:46:09.995",
          "mixer_motor_temperature_M1": 12.9,
          "mixer_motor_temperature_M2": 18.4,
          "mixer_speed_M1": 120.8128,
          "mixer_speed_M2": 120.0389,
          "mixer_torque_M1": 6.6835,
          "mixer_torque_M2": 8.7226
     },
     "140": {
          "Time": "10:46:10.754",
          "mixer_motor_temperature_M1": 13.6,
          "mixer_motor_temperature_M2": 18.8,
          "mixer_speed_M1": 120.2202,
          "mixer_speed_M2": 121.0067,
          "mixer_torque_M1": 6.4192,
          "mixer_torque_M2": 6.3814
     },
     "141": {
          "Time": "10:46:11.513",
          "mixer_motor_temperature_M1": 13.6,
          "mixer_motor_temperature_M2": 18.6,
          "mixer_speed_M1": 120.05,
          "mixer_speed_M2": 120.0534,
          "mixer_torque_M1": 7.6653,
          "mixer_torque_M2": 8.496
     },
     "142": {
          "Time": "10:46:12.275",
          "mixer_motor_temperature_M1": 14.1,
          "mixer_motor_temperature_M2": 18.4,
          "mixer_speed_M1": 120.0546,
          "mixer_speed_M2": 120.2604,
          "mixer_torque_M1": 6.8346,
          "mixer_torque_M2": 6.9478
     },
     "143": {
          "Time": "10:46:13.035",
          "mixer_motor_temperature_M1": 13.4,
          "mixer_motor_temperature_M2": 18.2,
          "mixer_speed_M1": 119.7748,
          "mixer_speed_M2": 120.157,
          "mixer_torque_M1": 6.8346,
          "mixer_torque_M2": 8.7226
     },
     "144": {
          "Time": "10:46:13.790",
          "mixer_motor_temperature_M1": 13.6,
          "mixer_motor_temperature_M2": 18.4,
          "mixer_speed_M1": 119.8144,
          "mixer_speed_M2": 120.3372,
          "mixer_torque_M1": 5.9283,
          "mixer_torque_M2": 8.5338
     },
     "145": {
          "Time": "10:46:14.554",
          "mixer_motor_temperature_M1": 13.8,
          "mixer_motor_temperature_M2": 18.2,
          "mixer_speed_M1": 119.5244,
          "mixer_speed_M2": 119.7518,
          "mixer_torque_M1": 6.3437,
          "mixer_torque_M2": 8.4205
     },
     "146": {
          "Time": "10:46:15.316",
          "mixer_motor_temperature_M1": 13.6,
          "mixer_motor_temperature_M2": 18.2,
          "mixer_speed_M1": 99.6094,
          "mixer_speed_M2": 99.5271,
          "mixer_torque_M1": 4.6822,
          "mixer_torque_M2": 5.7773
     },
     "147": {
          "Time": "10:46:16.083",
          "mixer_motor_temperature_M1": 13.6,
          "mixer_motor_temperature_M2": 18.6,
          "mixer_speed_M1": 99.7698,
          "mixer_speed_M2": 99.0871,
          "mixer_torque_M1": 5.3242,
          "mixer_torque_M2": 8.0806
     },
     "148": {
          "Time": "10:46:16.844",
          "mixer_motor_temperature_M1": 14.1,
          "mixer_motor_temperature_M2": 18.8,
          "mixer_speed_M1": 100.2187,
          "mixer_speed_M2": 99.3291,
          "mixer_torque_M1": 6.1549,
          "mixer_torque_M2": 7.6653
     },
     "149": {
          "Time": "10:46:17.604",
          "mixer_motor_temperature_M1": 13.6,
          "mixer_motor_temperature_M2": 18.2,
          "mixer_speed_M1": 99.9027,
          "mixer_speed_M2": 100.1521,
          "mixer_torque_M1": 5.6262,
          "mixer_torque_M2": 7.401
     },
     "150": {
          "Time": "10:46:18.365",
          "mixer_motor_temperature_M1": 13.8,
          "mixer_motor_temperature_M2": 19.1,
          "mixer_speed_M1": 99.8257,
          "mixer_speed_M2": 100.5523,
          "mixer_torque_M1": 5.0598,
          "mixer_torque_M2": 5.1731
     },
     "151": {
          "Time": "10:46:19.126",
          "mixer_motor_temperature_M1": 13.6,
          "mixer_motor_temperature_M2": 18.6,
          "mixer_speed_M1": 99.282,
          "mixer_speed_M2": 99.409,
          "mixer_torque_M1": 6.2682,
          "mixer_torque_M2": 7.401
     },
     "152": {
          "Time": "10:46:19.890",
          "mixer_motor_temperature_M1": 14.1,
          "mixer_motor_temperature_M2": 18.6,
          "mixer_speed_M1": 99.4618,
          "mixer_speed_M2": 99.8598,
          "mixer_torque_M1": 5.664,
          "mixer_torque_M2": 8.3827
     },
     "153": {
          "Time": "10:46:20.652",
          "mixer_motor_temperature_M1": 13.6,
          "mixer_motor_temperature_M2": 19.1,
          "mixer_speed_M1": 99.641,
          "mixer_speed_M2": 99.6453,
          "mixer_torque_M1": 6.2304,
          "mixer_torque_M2": 7.401
     },
     "154": {
          "Time": "10:46:21.416",
          "mixer_motor_temperature_M1": 14.1,
          "mixer_motor_temperature_M2": 18.6,
          "mixer_speed_M1": 99.7067,
          "mixer_speed_M2": 99.6504,
          "mixer_torque_M1": 5.8906,
          "mixer_torque_M2": 5.7773
     },
     "155": {
          "Time": "10:46:22.178",
          "mixer_motor_temperature_M1": 14.1,
          "mixer_motor_temperature_M2": 18.6,
          "mixer_speed_M1": 99.1184,
          "mixer_speed_M2": 100.0495,
          "mixer_torque_M1": 6.3059,
          "mixer_torque_M2": 8.1939
     },
     "156": {
          "Time": "10:46:22.936",
          "mixer_motor_temperature_M1": 13.8,
          "mixer_motor_temperature_M2": 18.6,
          "mixer_speed_M1": 99.1537,
          "mixer_speed_M2": 99.652,
          "mixer_torque_M1": 5.9661,
          "mixer_torque_M2": 7.7786
     },
     "157": {
          "Time": "10:46:23.698",
          "mixer_motor_temperature_M1": 13.6,
          "mixer_motor_temperature_M2": 18.8,
          "mixer_speed_M1": 99.6151,
          "mixer_speed_M2": 99.8727,
          "mixer_torque_M1": 4.6822,
          "mixer_torque_M2": 7.1366
     },
     "158": {
          "Time": "10:46:24.459",
          "mixer_motor_temperature_M1": 14.1,
          "mixer_motor_temperature_M2": 19.1,
          "mixer_speed_M1": 99.8347,
          "mixer_speed_M2": 99.3174,
          "mixer_torque_M1": 6.7213,
          "mixer_torque_M2": 6.1549
     },
     "159": {
          "Time": "10:46:25.220",
          "mixer_motor_temperature_M1": 13.8,
          "mixer_motor_temperature_M2": 18.6,
          "mixer_speed_M1": 98.6859,
          "mixer_speed_M2": 99.5322,
          "mixer_torque_M1": 6.1171,
          "mixer_torque_M2": 8.0051
     },
     "160": {
          "Time": "10:46:25.979",
          "mixer_motor_temperature_M1": 13.6,
          "mixer_motor_temperature_M2": 18.6,
          "mixer_speed_M1": 99.638,
          "mixer_speed_M2": 99.5716,
          "mixer_torque_M1": 5.6262,
          "mixer_torque_M2": 9.1757
     },
     "161": {
          "Time": "10:46:26.743",
          "mixer_motor_temperature_M1": 13.2,
          "mixer_motor_temperature_M2": 19.1,
          "mixer_speed_M1": 99.69,
          "mixer_speed_M2": 99.5683,
          "mixer_torque_M1": 4.569,
          "mixer_torque_M2": 7.5898
     },
     "162": {
          "Time": "10:46:27.502",
          "mixer_motor_temperature_M1": 14.3,
          "mixer_motor_temperature_M2": 18.8,
          "mixer_speed_M1": 99.9669,
          "mixer_speed_M2": 98.8779,
          "mixer_torque_M1": 5.7395,
          "mixer_torque_M2": 7.9674
     },
     "163": {
          "Time": "10:46:28.262",
          "mixer_motor_temperature_M1": 14.1,
          "mixer_motor_temperature_M2": 18.8,
          "mixer_speed_M1": 99.9587,
          "mixer_speed_M2": 99.1443,
          "mixer_torque_M1": 6.3814,
          "mixer_torque_M2": 7.4387
     },
     "164": {
          "Time": "10:46:29.024",
          "mixer_motor_temperature_M1": 13.6,
          "mixer_motor_temperature_M2": 18.8,
          "mixer_speed_M1": 99.4645,
          "mixer_speed_M2": 99.8673,
          "mixer_torque_M1": 5.2486,
          "mixer_torque_M2": 7.7786
     },
     "165": {
          "Time": "10:46:29.781",
          "mixer_motor_temperature_M1": 14.5,
          "mixer_motor_temperature_M2": 18.8,
          "mixer_speed_M1": 98.0344,
          "mixer_speed_M2": 81.5347,
          "mixer_torque_M1": 3.927,
          "mixer_torque_M2": 6.6835
     },
     "166": {
          "Time": "10:46:30.541",
          "mixer_motor_temperature_M1": 14.5,
          "mixer_motor_temperature_M2": 18.6,
          "mixer_speed_M1": 80.268,
          "mixer_speed_M2": 80.4481,
          "mixer_torque_M1": 3.2096,
          "mixer_torque_M2": 6.1171
     },
     "167": {
          "Time": "10:46:31.307",
          "mixer_motor_temperature_M1": 13.6,
          "mixer_motor_temperature_M2": 18.6,
          "mixer_speed_M1": 80.1974,
          "mixer_speed_M2": 80.5572,
          "mixer_torque_M1": 4.0403,
          "mixer_torque_M2": 6.2304
     },
     "168": {
          "Time": "10:46:32.067",
          "mixer_motor_temperature_M1": 14.1,
          "mixer_motor_temperature_M2": 19.1,
          "mixer_speed_M1": 80.202,
          "mixer_speed_M2": 81.1082,
          "mixer_torque_M1": 3.5494,
          "mixer_torque_M2": 5.8906
     },
     "169": {
          "Time": "10:46:32.863",
          "mixer_motor_temperature_M1": 14.1,
          "mixer_motor_temperature_M2": 18.6,
          "mixer_speed_M1": 80.1203,
          "mixer_speed_M2": 80.4451,
          "mixer_torque_M1": 4.9843,
          "mixer_torque_M2": 4.8333
     },
     "170": {
          "Time": "10:46:33.625",
          "mixer_motor_temperature_M1": 15.0,
          "mixer_motor_temperature_M2": 19.1,
          "mixer_speed_M1": 80.4095,
          "mixer_speed_M2": 80.6209,
          "mixer_torque_M1": 4.6822,
          "mixer_torque_M2": 4.6822
     },
     "171": {
          "Time": "10:46:34.389",
          "mixer_motor_temperature_M1": 13.6,
          "mixer_motor_temperature_M2": 18.6,
          "mixer_speed_M1": 80.836,
          "mixer_speed_M2": 80.1413,
          "mixer_torque_M1": 4.7955,
          "mixer_torque_M2": 5.2109
     },
     "172": {
          "Time": "10:46:35.157",
          "mixer_motor_temperature_M1": 13.6,
          "mixer_motor_temperature_M2": 19.1,
          "mixer_speed_M1": 80.7125,
          "mixer_speed_M2": 79.8964,
          "mixer_torque_M1": 4.4934,
          "mixer_torque_M2": 5.5507
     },
     "173": {
          "Time": "10:46:35.918",
          "mixer_motor_temperature_M1": 13.6,
          "mixer_motor_temperature_M2": 19.1,
          "mixer_speed_M1": 80.5056,
          "mixer_speed_M2": 79.8327,
          "mixer_torque_M1": 5.2109,
          "mixer_torque_M2": 5.1354
     },
     "174": {
          "Time": "10:46:36.712",
          "mixer_motor_temperature_M1": 14.5,
          "mixer_motor_temperature_M2": 19.1,
          "mixer_speed_M1": 80.1368,
          "mixer_speed_M2": 80.467,
          "mixer_torque_M1": 4.72,
          "mixer_torque_M2": 6.9478
     },
     "175": {
          "Time": "10:46:37.456",
          "mixer_motor_temperature_M1": 14.3,
          "mixer_motor_temperature_M2": 19.1,
          "mixer_speed_M1": 80.2838,
          "mixer_speed_M2": 80.3083,
          "mixer_torque_M1": 4.6445,
          "mixer_torque_M2": 6.3814
     },
     "176": {
          "Time": "10:46:38.222",
          "mixer_motor_temperature_M1": 13.8,
          "mixer_motor_temperature_M2": 19.1,
          "mixer_speed_M1": 80.0524,
          "mixer_speed_M2": 80.8333,
          "mixer_torque_M1": 4.9466,
          "mixer_torque_M2": 6.7213
     },
     "177": {
          "Time": "10:46:38.996",
          "mixer_motor_temperature_M1": 13.8,
          "mixer_motor_temperature_M2": 19.1,
          "mixer_speed_M1": 80.0773,
          "mixer_speed_M2": 80.3821,
          "mixer_torque_M1": 4.871,
          "mixer_torque_M2": 7.3632
     },
     "178": {
          "Time": "10:46:39.756",
          "mixer_motor_temperature_M1": 13.4,
          "mixer_motor_temperature_M2": 19.1,
          "mixer_speed_M1": 79.9333,
          "mixer_speed_M2": 80.8002,
          "mixer_torque_M1": 5.8906,
          "mixer_torque_M2": 6.3814
     },
     "179": {
          "Time": "10:46:40.519",
          "mixer_motor_temperature_M1": 13.6,
          "mixer_motor_temperature_M2": 19.3,
          "mixer_speed_M1": 79.964,
          "mixer_speed_M2": 80.4254,
          "mixer_torque_M1": 4.72,
          "mixer_torque_M2": 7.3254
     },
     "180": {
          "Time": "10:46:41.280",
          "mixer_motor_temperature_M1": 13.6,
          "mixer_motor_temperature_M2": 19.1,
          "mixer_speed_M1": 80.0534,
          "mixer_speed_M2": 80.5493,
          "mixer_torque_M1": 4.9088,
          "mixer_torque_M2": 6.1926
     },
     "181": {
          "Time": "10:46:42.046",
          "mixer_motor_temperature_M1": 14.1,
          "mixer_motor_temperature_M2": 18.6,
          "mixer_speed_M1": 80.6122,
          "mixer_speed_M2": 80.5036,
          "mixer_torque_M1": 5.513,
          "mixer_torque_M2": 6.759
     },
     "182": {
          "Time": "10:46:42.811",
          "mixer_motor_temperature_M1": 14.1,
          "mixer_motor_temperature_M2": 19.1,
          "mixer_speed_M1": 81.2461,
          "mixer_speed_M2": 80.0796,
          "mixer_torque_M1": 5.0976,
          "mixer_torque_M2": 6.8346
     },
     "183": {
          "Time": "10:46:43.573",
          "mixer_motor_temperature_M1": 14.1,
          "mixer_motor_temperature_M2": 18.6,
          "mixer_speed_M1": 79.9886,
          "mixer_speed_M2": 79.7268,
          "mixer_torque_M1": 5.6262,
          "mixer_torque_M2": 6.6458
     },
     "184": {
          "Time": "10:46:44.335",
          "mixer_motor_temperature_M1": 13.4,
          "mixer_motor_temperature_M2": 19.1,
          "mixer_speed_M1": 81.0807,
          "mixer_speed_M2": 80.0407,
          "mixer_torque_M1": 5.2486,
          "mixer_torque_M2": 6.5702
     },
     "185": {
          "Time": "10:46:45.099",
          "mixer_motor_temperature_M1": 14.1,
          "mixer_motor_temperature_M2": 18.6,
          "mixer_speed_M1": 60.0558,
          "mixer_speed_M2": 61.0799,
          "mixer_torque_M1": 4.5312,
          "mixer_torque_M2": 5.6262
     },
     "186": {
          "Time": "10:46:45.860",
          "mixer_motor_temperature_M1": 14.1,
          "mixer_motor_temperature_M2": 19.1,
          "mixer_speed_M1": 60.1765,
          "mixer_speed_M2": 59.8466,
          "mixer_torque_M1": 3.8893,
          "mixer_torque_M2": 4.871
     },
     "187": {
          "Time": "10:46:46.621",
          "mixer_motor_temperature_M1": 14.8,
          "mixer_motor_temperature_M2": 19.1,
          "mixer_speed_M1": 60.0798,
          "mixer_speed_M2": 59.9777,
          "mixer_torque_M1": 4.3802,
          "mixer_torque_M2": 5.9661
     },
     "188": {
          "Time": "10:46:47.383",
          "mixer_motor_temperature_M1": 14.5,
          "mixer_motor_temperature_M2": 18.6,
          "mixer_speed_M1": 60.0797,
          "mixer_speed_M2": 59.8893,
          "mixer_torque_M1": 4.5312,
          "mixer_torque_M2": 5.815
     },
     "189": {
          "Time": "10:46:48.162",
          "mixer_motor_temperature_M1": 14.1,
          "mixer_motor_temperature_M2": 18.8,
          "mixer_speed_M1": 60.1401,
          "mixer_speed_M2": 59.8519,
          "mixer_torque_M1": 4.3424,
          "mixer_torque_M2": 5.3619
     },
     "190": {
          "Time": "10:46:48.928",
          "mixer_motor_temperature_M1": 13.8,
          "mixer_motor_temperature_M2": 19.3,
          "mixer_speed_M1": 60.0232,
          "mixer_speed_M2": 59.6444,
          "mixer_torque_M1": 3.7005,
          "mixer_torque_M2": 4.1536
     },
     "191": {
          "Time": "10:46:49.689",
          "mixer_motor_temperature_M1": 14.3,
          "mixer_motor_temperature_M2": 19.1,
          "mixer_speed_M1": 60.1722,
          "mixer_speed_M2": 60.2011,
          "mixer_torque_M1": 3.4739,
          "mixer_torque_M2": 5.4752
     },
     "192": {
          "Time": "10:46:50.466",
          "mixer_motor_temperature_M1": 14.1,
          "mixer_motor_temperature_M2": 18.4,
          "mixer_speed_M1": 59.9053,
          "mixer_speed_M2": 59.9944,
          "mixer_torque_M1": 4.7578,
          "mixer_torque_M2": 6.3059
     },
     "193": {
          "Time": "10:46:51.240",
          "mixer_motor_temperature_M1": 14.3,
          "mixer_motor_temperature_M2": 18.6,
          "mixer_speed_M1": 59.9459,
          "mixer_speed_M2": 60.0115,
          "mixer_torque_M1": 4.871,
          "mixer_torque_M2": 5.9283
     },
     "194": {
          "Time": "10:46:52.012",
          "mixer_motor_temperature_M1": 14.3,
          "mixer_motor_temperature_M2": 19.1,
          "mixer_speed_M1": 59.7495,
          "mixer_speed_M2": 60.1305,
          "mixer_torque_M1": 4.2669,
          "mixer_torque_M2": 5.3242
     },
     "195": {
          "Time": "10:46:52.743",
          "mixer_motor_temperature_M1": 13.8,
          "mixer_motor_temperature_M2": 19.1,
          "mixer_speed_M1": 59.9577,
          "mixer_speed_M2": 60.2552,
          "mixer_torque_M1": 4.0026,
          "mixer_torque_M2": 5.7773
     },
     "196": {
          "Time": "10:46:53.501",
          "mixer_motor_temperature_M1": 14.3,
          "mixer_motor_temperature_M2": 18.8,
          "mixer_speed_M1": 60.0266,
          "mixer_speed_M2": 59.9347,
          "mixer_torque_M1": 4.3424,
          "mixer_torque_M2": 6.2682
     },
     "197": {
          "Time": "10:46:54.259",
          "mixer_motor_temperature_M1": 13.6,
          "mixer_motor_temperature_M2": 19.1,
          "mixer_speed_M1": 60.0429,
          "mixer_speed_M2": 60.1308,
          "mixer_torque_M1": 4.9843,
          "mixer_torque_M2": 6.0038
     },
     "198": {
          "Time": "10:46:55.016",
          "mixer_motor_temperature_M1": 13.6,
          "mixer_motor_temperature_M2": 18.8,
          "mixer_speed_M1": 59.9453,
          "mixer_speed_M2": 59.8599,
          "mixer_torque_M1": 3.8893,
          "mixer_torque_M2": 5.0598
     },
     "199": {
          "Time": "10:46:55.778",
          "mixer_motor_temperature_M1": 14.1,
          "mixer_motor_temperature_M2": 18.8,
          "mixer_speed_M1": 59.8899,
          "mixer_speed_M2": 60.1125,
          "mixer_torque_M1": 3.3606,
          "mixer_torque_M2": 5.1354
     },
     "200": {
          "Time": "10:46:56.540",
          "mixer_motor_temperature_M1": 14.1,
          "mixer_motor_temperature_M2": 18.6,
          "mixer_speed_M1": 60.0355,
          "mixer_speed_M2": 60.0826,
          "mixer_torque_M1": 4.3046,
          "mixer_torque_M2": 5.513
     },
     "201": {
          "Time": "10:46:57.303",
          "mixer_motor_temperature_M1": 14.1,
          "mixer_motor_temperature_M2": 19.1,
          "mixer_speed_M1": 60.3465,
          "mixer_speed_M2": 59.7761,
          "mixer_torque_M1": 4.5312,
          "mixer_torque_M2": 5.5885
     },
     "202": {
          "Time": "10:46:58.083",
          "mixer_motor_temperature_M1": 14.3,
          "mixer_motor_temperature_M2": 18.6,
          "mixer_speed_M1": 59.7409,
          "mixer_speed_M2": 60.0446,
          "mixer_torque_M1": 4.5312,
          "mixer_torque_M2": 5.9283
     },
     "203": {
          "Time": "10:46:58.864",
          "mixer_motor_temperature_M1": 13.6,
          "mixer_motor_temperature_M2": 18.6,
          "mixer_speed_M1": 60.1729,
          "mixer_speed_M2": 59.8415,
          "mixer_torque_M1": 3.8893,
          "mixer_torque_M2": 4.8333
     },
     "204": {
          "Time": "10:46:59.629",
          "mixer_motor_temperature_M1": 14.5,
          "mixer_motor_temperature_M2": 18.8,
          "mixer_speed_M1": 59.9519,
          "mixer_speed_M2": 60.072,
          "mixer_torque_M1": 3.3229,
          "mixer_torque_M2": 4.6822
     },
     "205": {
          "Time": "10:47:00.392",
          "mixer_motor_temperature_M1": 14.3,
          "mixer_motor_temperature_M2": 19.1,
          "mixer_speed_M1": 39.5513,
          "mixer_speed_M2": 39.7251,
          "mixer_torque_M1": 3.8138,
          "mixer_torque_M2": 4.8333
     },
     "206": {
          "Time": "10:47:01.155",
          "mixer_motor_temperature_M1": 14.5,
          "mixer_motor_temperature_M2": 18.6,
          "mixer_speed_M1": 39.5162,
          "mixer_speed_M2": 39.2589,
          "mixer_torque_M1": 3.1718,
          "mixer_torque_M2": 4.4934
     },
     "207": {
          "Time": "10:47:01.916",
          "mixer_motor_temperature_M1": 14.3,
          "mixer_motor_temperature_M2": 19.1,
          "mixer_speed_M1": 39.553,
          "mixer_speed_M2": 39.4083,
          "mixer_torque_M1": 3.6627,
          "mixer_torque_M2": 5.9283
     },
     "208": {
          "Time": "10:47:02.679",
          "mixer_motor_temperature_M1": 13.6,
          "mixer_motor_temperature_M2": 18.6,
          "mixer_speed_M1": 39.575,
          "mixer_speed_M2": 39.4668,
          "mixer_torque_M1": 3.5494,
          "mixer_torque_M2": 4.7578
     },
     "209": {
          "Time": "10:47:03.442",
          "mixer_motor_temperature_M1": 14.5,
          "mixer_motor_temperature_M2": 18.6,
          "mixer_speed_M1": 39.5236,
          "mixer_speed_M2": 39.4699,
          "mixer_torque_M1": 3.625,
          "mixer_torque_M2": 4.6822
     },
     "210": {
          "Time": "10:47:04.205",
          "mixer_motor_temperature_M1": 14.5,
          "mixer_motor_temperature_M2": 18.8,
          "mixer_speed_M1": 39.5788,
          "mixer_speed_M2": 39.8698,
          "mixer_torque_M1": 3.3984,
          "mixer_torque_M2": 5.1731
     },
     "211": {
          "Time": "10:47:04.969",
          "mixer_motor_temperature_M1": 14.1,
          "mixer_motor_temperature_M2": 18.6,
          "mixer_speed_M1": 39.608,
          "mixer_speed_M2": 39.6024,
          "mixer_torque_M1": 4.0781,
          "mixer_torque_M2": 4.6822
     },
     "212": {
          "Time": "10:47:05.712",
          "mixer_motor_temperature_M1": 14.5,
          "mixer_motor_temperature_M2": 19.1,
          "mixer_speed_M1": 39.6374,
          "mixer_speed_M2": 39.6208,
          "mixer_torque_M1": 3.5117,
          "mixer_torque_M2": 5.4752
     },
     "213": {
          "Time": "10:47:06.472",
          "mixer_motor_temperature_M1": 14.1,
          "mixer_motor_temperature_M2": 18.6,
          "mixer_speed_M1": 39.6789,
          "mixer_speed_M2": 39.7659,
          "mixer_torque_M1": 4.0403,
          "mixer_torque_M2": 4.6822
     },
     "214": {
          "Time": "10:47:07.263",
          "mixer_motor_temperature_M1": 14.5,
          "mixer_motor_temperature_M2": 19.1,
          "mixer_speed_M1": 39.3343,
          "mixer_speed_M2": 39.7186,
          "mixer_torque_M1": 2.8698,
          "mixer_torque_M2": 4.1536
     },
     "215": {
          "Time": "10:47:08.018",
          "mixer_motor_temperature_M1": 13.6,
          "mixer_motor_temperature_M2": 18.6,
          "mixer_speed_M1": 39.614,
          "mixer_speed_M2": 39.5273,
          "mixer_torque_M1": 3.776,
          "mixer_torque_M2": 5.1731
     },
     "216": {
          "Time": "10:47:08.779",
          "mixer_motor_temperature_M1": 14.8,
          "mixer_motor_temperature_M2": 19.1,
          "mixer_speed_M1": 39.7568,
          "mixer_speed_M2": 39.3587,
          "mixer_torque_M1": 3.1718,
          "mixer_torque_M2": 4.9843
     },
     "217": {
          "Time": "10:47:09.523",
          "mixer_motor_temperature_M1": 14.1,
          "mixer_motor_temperature_M2": 18.6,
          "mixer_speed_M1": 39.7043,
          "mixer_speed_M2": 39.4243,
          "mixer_torque_M1": 3.927,
          "mixer_torque_M2": 5.0221
     },
     "218": {
          "Time": "10:47:10.286",
          "mixer_motor_temperature_M1": 14.3,
          "mixer_motor_temperature_M2": 18.6,
          "mixer_speed_M1": 39.4877,
          "mixer_speed_M2": 39.4846,
          "mixer_torque_M1": 3.7382,
          "mixer_torque_M2": 4.3802
     },
     "219": {
          "Time": "10:47:11.065",
          "mixer_motor_temperature_M1": 14.8,
          "mixer_motor_temperature_M2": 19.1,
          "mixer_speed_M1": 39.6215,
          "mixer_speed_M2": 39.4336,
          "mixer_torque_M1": 4.1914,
          "mixer_torque_M2": 4.6067
     },
     "220": {
          "Time": "10:47:11.828",
          "mixer_motor_temperature_M1": 15.0,
          "mixer_motor_temperature_M2": 18.6,
          "mixer_speed_M1": 39.5437,
          "mixer_speed_M2": 39.4393,
          "mixer_torque_M1": 3.0963,
          "mixer_torque_M2": 4.7955
     },
     "221": {
          "Time": "10:47:12.602",
          "mixer_motor_temperature_M1": 13.6,
          "mixer_motor_temperature_M2": 18.6,
          "mixer_speed_M1": 39.7888,
          "mixer_speed_M2": 39.3085,
          "mixer_torque_M1": 4.0026,
          "mixer_torque_M2": 5.513
     },
     "222": {
          "Time": "10:47:13.369",
          "mixer_motor_temperature_M1": 13.6,
          "mixer_motor_temperature_M2": 19.1,
          "mixer_speed_M1": 39.8682,
          "mixer_speed_M2": 39.7203,
          "mixer_torque_M1": 3.0963,
          "mixer_torque_M2": 4.0781
     },
     "223": {
          "Time": "10:47:14.123",
          "mixer_motor_temperature_M1": 14.5,
          "mixer_motor_temperature_M2": 19.1,
          "mixer_speed_M1": 39.4467,
          "mixer_speed_M2": 39.4901,
          "mixer_torque_M1": 4.7578,
          "mixer_torque_M2": 4.0781
     },
     "224": {
          "Time": "10:47:14.884",
          "mixer_motor_temperature_M1": 14.5,
          "mixer_motor_temperature_M2": 18.8,
          "mixer_speed_M1": 24.2454,
          "mixer_speed_M2": 20.1186,
          "mixer_torque_M1": 2.4544,
          "mixer_torque_M2": 2.983
     },
     "225": {
          "Time": "10:47:15.645",
          "mixer_motor_temperature_M1": 14.3,
          "mixer_motor_temperature_M2": 18.6,
          "mixer_speed_M1": 20.2825,
          "mixer_speed_M2": 20.3875,
          "mixer_torque_M1": 2.5299,
          "mixer_torque_M2": 2.832
     },
     "226": {
          "Time": "10:47:16.422",
          "mixer_motor_temperature_M1": 14.3,
          "mixer_motor_temperature_M2": 18.6,
          "mixer_speed_M1": 20.3756,
          "mixer_speed_M2": 20.4222,
          "mixer_torque_M1": 2.4922,
          "mixer_torque_M2": 4.1536
     },
     "227": {
          "Time": "10:47:17.184",
          "mixer_motor_temperature_M1": 14.1,
          "mixer_motor_temperature_M2": 18.2,
          "mixer_speed_M1": 20.5163,
          "mixer_speed_M2": 20.4246,
          "mixer_torque_M1": 2.9075,
          "mixer_torque_M2": 2.7187
     },
     "228": {
          "Time": "10:47:17.967",
          "mixer_motor_temperature_M1": 14.8,
          "mixer_motor_temperature_M2": 18.6,
          "mixer_speed_M1": 20.4592,
          "mixer_speed_M2": 20.6402,
          "mixer_torque_M1": 2.4544,
          "mixer_torque_M2": 3.7005
     },
     "229": {
          "Time": "10:47:18.729",
          "mixer_motor_temperature_M1": 13.6,
          "mixer_motor_temperature_M2": 18.4,
          "mixer_speed_M1": 20.3874,
          "mixer_speed_M2": 20.2783,
          "mixer_torque_M1": 3.3606,
          "mixer_torque_M2": 3.1341
     },
     "230": {
          "Time": "10:47:19.509",
          "mixer_motor_temperature_M1": 13.2,
          "mixer_motor_temperature_M2": 18.6,
          "mixer_speed_M1": 20.4032,
          "mixer_speed_M2": 20.3815,
          "mixer_torque_M1": 2.2278,
          "mixer_torque_M2": 4.4557
     },
     "231": {
          "Time": "10:47:20.270",
          "mixer_motor_temperature_M1": 14.1,
          "mixer_motor_temperature_M2": 18.6,
          "mixer_speed_M1": 20.2312,
          "mixer_speed_M2": 20.3506,
          "mixer_torque_M1": 2.6432,
          "mixer_torque_M2": 3.3229
     },
     "232": {
          "Time": "10:47:21.031",
          "mixer_motor_temperature_M1": 14.1,
          "mixer_motor_temperature_M2": 18.6,
          "mixer_speed_M1": 20.4549,
          "mixer_speed_M2": 20.4101,
          "mixer_torque_M1": 1.8502,
          "mixer_torque_M2": 3.625
     },
     "233": {
          "Time": "10:47:21.793",
          "mixer_motor_temperature_M1": 14.3,
          "mixer_motor_temperature_M2": 18.6,
          "mixer_speed_M1": 20.1734,
          "mixer_speed_M2": 20.2668,
          "mixer_torque_M1": 2.681,
          "mixer_torque_M2": 2.9075
     },
     "234": {
          "Time": "10:47:22.569",
          "mixer_motor_temperature_M1": 14.1,
          "mixer_motor_temperature_M2": 18.2,
          "mixer_speed_M1": 20.5381,
          "mixer_speed_M2": 20.3911,
          "mixer_torque_M1": 3.1718,
          "mixer_torque_M2": 3.776
     },
     "235": {
          "Time": "10:47:23.330",
          "mixer_motor_temperature_M1": 14.1,
          "mixer_motor_temperature_M2": 18.6,
          "mixer_speed_M1": 20.2667,
          "mixer_speed_M2": 20.5089,
          "mixer_torque_M1": 2.1901,
          "mixer_torque_M2": 3.7382
     },
     "236": {
          "Time": "10:47:24.094",
          "mixer_motor_temperature_M1": 13.8,
          "mixer_motor_temperature_M2": 18.6,
          "mixer_speed_M1": 20.3411,
          "mixer_speed_M2": 20.3111,
          "mixer_torque_M1": 2.3034,
          "mixer_torque_M2": 3.3984
     },
     "237": {
          "Time": "10:47:24.852",
          "mixer_motor_temperature_M1": 13.6,
          "mixer_motor_temperature_M2": 18.4,
          "mixer_speed_M1": 20.3689,
          "mixer_speed_M2": 20.3551,
          "mixer_torque_M1": 2.3789,
          "mixer_torque_M2": 2.7187
     },
     "238": {
          "Time": "10:47:25.612",
          "mixer_motor_temperature_M1": 13.6,
          "mixer_motor_temperature_M2": 18.6,
          "mixer_speed_M1": 20.3874,
          "mixer_speed_M2": 20.6325,
          "mixer_torque_M1": 2.8698,
          "mixer_torque_M2": 5.0598
     },
     "239": {
          "Time": "10:47:26.373",
          "mixer_motor_temperature_M1": 13.6,
          "mixer_motor_temperature_M2": 18.2,
          "mixer_speed_M1": 20.6852,
          "mixer_speed_M2": 20.2698,
          "mixer_torque_M1": 2.7187,
          "mixer_torque_M2": 3.0586
     },
     "240": {
          "Time": "10:47:27.133",
          "mixer_motor_temperature_M1": 14.5,
          "mixer_motor_temperature_M2": 18.2,
          "mixer_speed_M1": 20.2972,
          "mixer_speed_M2": 20.2736,
          "mixer_torque_M1": 2.0013,
          "mixer_torque_M2": 3.8138
     },
     "241": {
          "Time": "10:47:27.891",
          "mixer_motor_temperature_M1": 13.6,
          "mixer_motor_temperature_M2": 18.6,
          "mixer_speed_M1": 20.633,
          "mixer_speed_M2": 20.1587,
          "mixer_torque_M1": 2.7942,
          "mixer_torque_M2": 3.5494
     },
     "242": {
          "Time": "10:47:28.652",
          "mixer_motor_temperature_M1": 13.6,
          "mixer_motor_temperature_M2": 18.4,
          "mixer_speed_M1": 20.4324,
          "mixer_speed_M2": 20.4143,
          "mixer_torque_M1": 3.0208,
          "mixer_torque_M2": 3.5494
     },
     "243": {
          "Time": "10:47:29.410",
          "mixer_motor_temperature_M1": 13.8,
          "mixer_motor_temperature_M2": 18.6,
          "mixer_speed_M1": 20.3562,
          "mixer_speed_M2": 20.4167,
          "mixer_torque_M1": 2.4166,
          "mixer_torque_M2": 3.5494
     }
}