{
     "1": {
          "Time": "11:21:06.634",
          "mixer_motor_temperature_M1": 14.8,
          "mixer_motor_temperature_M2": 17.7,
          "mixer_speed_M1": 20.1448,
          "mixer_speed_M2": 20.2782,
          "mixer_torque_M1": 1.5482,
          "mixer_torque_M2": 2.3411
     },
     "2": {
          "Time": "11:21:07.588",
          "mixer_motor_temperature_M1": 15.0,
          "mixer_motor_temperature_M2": 17.5,
          "mixer_speed_M1": 20.2593,
          "mixer_speed_M2": 20.7857,
          "mixer_torque_M1": 1.9635,
          "mixer_torque_M2": 1.7747
     },
     "3": {
          "Time": "11:21:08.352",
          "mixer_motor_temperature_M1": 15.0,
          "mixer_motor_temperature_M2": 17.5,
          "mixer_speed_M1": 20.4424,
          "mixer_speed_M2": 20.3598,
          "mixer_torque_M1": 2.7942,
          "mixer_torque_M2": 2.1523
     },
     "4": {
          "Time": "11:21:09.113",
          "mixer_motor_temperature_M1": 15.0,
          "mixer_motor_temperature_M2": 17.5,
          "mixer_speed_M1": 20.3694,
          "mixer_speed_M2": 20.4767,
          "mixer_torque_M1": 2.6432,
          "mixer_torque_M2": 3.3229
     },
     "5": {
          "Time": "11:21:09.876",
          "mixer_motor_temperature_M1": 15.0,
          "mixer_motor_temperature_M2": 17.5,
          "mixer_speed_M1": 20.5926,
          "mixer_speed_M2": 20.3167,
          "mixer_torque_M1": 1.7747,
          "mixer_torque_M2": 2.9453
     },
     "6": {
          "Time": "11:21:10.636",
          "mixer_motor_temperature_M1": 15.2,
          "mixer_motor_temperature_M2": 17.5,
          "mixer_speed_M1": 20.407,
          "mixer_speed_M2": 20.2329,
          "mixer_torque_M1": 1.9258,
          "mixer_torque_M2": 1.4349
     },
     "7": {
          "Time": "11:21:11.412",
          "mixer_motor_temperature_M1": 14.8,
          "mixer_motor_temperature_M2": 17.7,
          "mixer_speed_M1": 20.3028,
          "mixer_speed_M2": 20.346,
          "mixer_torque_M1": 2.7187,
          "mixer_torque_M2": 2.3034
     },
     "8": {
          "Time": "11:21:12.177",
          "mixer_motor_temperature_M1": 14.3,
          "mixer_motor_temperature_M2": 17.9,
          "mixer_speed_M1": 20.2247,
          "mixer_speed_M2": 20.9728,
          "mixer_torque_M1": 2.4166,
          "mixer_torque_M2": 2.7942
     },
     "9": {
          "Time": "11:21:12.942",
          "mixer_motor_temperature_M1": 15.0,
          "mixer_motor_temperature_M2": 17.5,
          "mixer_speed_M1": 20.1746,
          "mixer_speed_M2": 20.1172,
          "mixer_torque_M1": 2.3034,
          "mixer_torque_M2": 2.5677
     },
     "10": {
          "Time": "11:21:13.704",
          "mixer_motor_temperature_M1": 14.1,
          "mixer_motor_temperature_M2": 17.7,
          "mixer_speed_M1": 20.3765,
          "mixer_speed_M2": 20.6857,
          "mixer_torque_M1": 2.3034,
          "mixer_torque_M2": 2.4544
     },
     "11": {
          "Time": "11:21:14.467",
          "mixer_motor_temperature_M1": 14.8,
          "mixer_motor_temperature_M2": 17.5,
          "mixer_speed_M1": 21.1653,
          "mixer_speed_M2": 20.4498,
          "mixer_torque_M1": 2.6054,
          "mixer_torque_M2": 2.0013
     },
     "12": {
          "Time": "11:21:15.231",
          "mixer_motor_temperature_M1": 15.0,
          "mixer_motor_temperature_M2": 17.9,
          "mixer_speed_M1": 20.4951,
          "mixer_speed_M2": 20.3638,
          "mixer_torque_M1": 2.1901,
          "mixer_torque_M2": 1.9258
     },
     "13": {
          "Time": "11:21:15.995",
          "mixer_motor_temperature_M1": 14.1,
          "mixer_motor_temperature_M2": 17.7,
          "mixer_speed_M1": 20.2737,
          "mixer_speed_M2": 20.442,
          "mixer_torque_M1": 2.0768,
          "mixer_torque_M2": 2.4166
     },
     "14": {
          "Time": "11:21:16.757",
          "mixer_motor_temperature_M1": 14.8,
          "mixer_motor_temperature_M2": 17.5,
          "mixer_speed_M1": 20.4639,
          "mixer_speed_M2": 20.3187,
          "mixer_torque_M1": 2.4922,
          "mixer_torque_M2": 2.5677
     },
     "15": {
          "Time": "11:21:17.523",
          "mixer_motor_temperature_M1": 15.0,
          "mixer_motor_temperature_M2": 17.5,
          "mixer_speed_M1": 20.2907,
          "mixer_speed_M2": 20.2246,
          "mixer_torque_M1": 3.2851,
          "mixer_torque_M2": 3.0208
     },
     "16": {
          "Time": "11:21:18.280",
          "mixer_motor_temperature_M1": 14.8,
          "mixer_motor_temperature_M2": 17.5,
          "mixer_speed_M1": 20.5722,
          "mixer_speed_M2": 20.4045,
          "mixer_torque_M1": 1.9258,
          "mixer_torque_M2": 2.9453
     },
     "17": {
          "Time": "11:21:19.046",
          "mixer_motor_temperature_M1": 15.0,
          "mixer_motor_temperature_M2": 17.5,
          "mixer_speed_M1": 20.3874,
          "mixer_speed_M2": 20.3906,
          "mixer_torque_M1": 2.0768,
          "mixer_torque_M2": 1.8125
     },
     "18": {
          "Time": "11:21:19.807",
          "mixer_motor_temperature_M1": 14.8,
          "mixer_motor_temperature_M2": 17.5,
          "mixer_speed_M1": 20.4136,
          "mixer_speed_M2": 20.3331,
          "mixer_torque_M1": 2.5677,
          "mixer_torque_M2": 3.2474
     },
     "19": {
          "Time": "11:21:20.569",
          "mixer_motor_temperature_M1": 15.0,
          "mixer_motor_temperature_M2": 17.7,
          "mixer_speed_M1": 20.8271,
          "mixer_speed_M2": 20.3035,
          "mixer_torque_M1": 3.2096,
          "mixer_torque_M2": 2.5677
     },
     "20": {
          "Time": "11:21:21.329",
          "mixer_motor_temperature_M1": 15.0,
          "mixer_motor_temperature_M2": 17.0,
          "mixer_speed_M1": 20.4213,
          "mixer_speed_M2": 20.3791,
          "mixer_torque_M1": 2.681,
          "mixer_torque_M2": 2.5677
     },
     "21": {
          "Time": "11:21:22.101",
          "mixer_motor_temperature_M1": 15.0,
          "mixer_motor_temperature_M2": 18.2,
          "mixer_speed_M1": 20.4155,
          "mixer_speed_M2": 20.3262,
          "mixer_torque_M1": 2.681,
          "mixer_torque_M2": 2.1523
     },
     "22": {
          "Time": "11:21:22.864",
          "mixer_motor_temperature_M1": 14.1,
          "mixer_motor_temperature_M2": 17.9,
          "mixer_speed_M1": 20.4388,
          "mixer_speed_M2": 20.3426,
          "mixer_torque_M1": 1.9635,
          "mixer_torque_M2": 2.3411
     },
     "23": {
          "Time": "11:21:23.624",
          "mixer_motor_temperature_M1": 14.8,
          "mixer_motor_temperature_M2": 17.5,
          "mixer_speed_M1": 20.5789,
          "mixer_speed_M2": 20.2427,
          "mixer_torque_M1": 2.5677,
          "mixer_torque_M2": 2.3789
     },
     "24": {
          "Time": "11:21:24.389",
          "mixer_motor_temperature_M1": 14.8,
          "mixer_motor_temperature_M2": 17.5,
          "mixer_speed_M1": 20.7517,
          "mixer_speed_M2": 20.5123,
          "mixer_torque_M1": 1.6992,
          "mixer_torque_M2": 2.4922
     },
     "25": {
          "Time": "11:21:25.151",
          "mixer_motor_temperature_M1": 14.8,
          "mixer_motor_temperature_M2": 17.7,
          "mixer_speed_M1": 20.8329,
          "mixer_speed_M2": 20.3897,
          "mixer_torque_M1": 2.4544,
          "mixer_torque_M2": 1.9258
     },
     "26": {
          "Time": "11:21:25.914",
          "mixer_motor_temperature_M1": 14.5,
          "mixer_motor_temperature_M2": 17.3,
          "mixer_speed_M1": 20.3668,
          "mixer_speed_M2": 20.4904,
          "mixer_torque_M1": 2.1523,
          "mixer_torque_M2": 3.0586
     },
     "27": {
          "Time": "11:21:26.675",
          "mixer_motor_temperature_M1": 14.8,
          "mixer_motor_temperature_M2": 17.7,
          "mixer_speed_M1": 20.4148,
          "mixer_speed_M2": 20.2506,
          "mixer_torque_M1": 2.8698,
          "mixer_torque_M2": 2.3789
     },
     "28": {
          "Time": "11:21:27.448",
          "mixer_motor_temperature_M1": 15.0,
          "mixer_motor_temperature_M2": 17.3,
          "mixer_speed_M1": 20.4106,
          "mixer_speed_M2": 20.4149,
          "mixer_torque_M1": 2.4166,
          "mixer_torque_M2": 2.3411
     },
     "29": {
          "Time": "11:21:28.190",
          "mixer_motor_temperature_M1": 14.8,
          "mixer_motor_temperature_M2": 18.2,
          "mixer_speed_M1": 20.3767,
          "mixer_speed_M2": 20.7069,
          "mixer_torque_M1": 2.8698,
          "mixer_torque_M2": 2.1523
     },
     "30": {
          "Time": "11:21:28.955",
          "mixer_motor_temperature_M1": 14.1,
          "mixer_motor_temperature_M2": 17.7,
          "mixer_speed_M1": 20.3433,
          "mixer_speed_M2": 19.9617,
          "mixer_torque_M1": 2.9453,
          "mixer_torque_M2": 2.9075
     },
     "31": {
          "Time": "11:21:29.719",
          "mixer_motor_temperature_M1": 14.8,
          "mixer_motor_temperature_M2": 17.7,
          "mixer_speed_M1": 20.1071,
          "mixer_speed_M2": 20.7295,
          "mixer_torque_M1": 2.6054,
          "mixer_torque_M2": 3.2474
     },
     "32": {
          "Time": "11:21:30.481",
          "mixer_motor_temperature_M1": 14.8,
          "mixer_motor_temperature_M2": 17.5,
          "mixer_speed_M1": 20.2008,
          "mixer_speed_M2": 20.3361,
          "mixer_torque_M1": 2.1523,
          "mixer_torque_M2": 2.4922
     },
     "33": {
          "Time": "11:21:31.243",
          "mixer_motor_temperature_M1": 14.5,
          "mixer_motor_temperature_M2": 17.9,
          "mixer_speed_M1": 20.954,
          "mixer_speed_M2": 20.1974,
          "mixer_torque_M1": 2.1901,
          "mixer_torque_M2": 2.2656
     },
     "34": {
          "Time": "11:21:32.011",
          "mixer_motor_temperature_M1": 15.4,
          "mixer_motor_temperature_M2": 17.5,
          "mixer_speed_M1": 20.4671,
          "mixer_speed_M2": 20.1749,
          "mixer_torque_M1": 2.7942,
          "mixer_torque_M2": 2.9453
     },
     "35": {
          "Time": "11:21:32.771",
          "mixer_motor_temperature_M1": 15.0,
          "mixer_motor_temperature_M2": 17.5,
          "mixer_speed_M1": 19.9915,
          "mixer_speed_M2": 20.3932,
          "mixer_torque_M1": 2.1901,
          "mixer_torque_M2": 2.2278
     },
     "36": {
          "Time": "11:21:33.535",
          "mixer_motor_temperature_M1": 14.5,
          "mixer_motor_temperature_M2": 17.3,
          "mixer_speed_M1": 20.3558,
          "mixer_speed_M2": 20.4288,
          "mixer_torque_M1": 1.9635,
          "mixer_torque_M2": 2.1146
     },
     "37": {
          "Time": "11:21:34.301",
          "mixer_motor_temperature_M1": 14.3,
          "mixer_motor_temperature_M2": 17.5,
          "mixer_speed_M1": 20.4515,
          "mixer_speed_M2": 20.679,
          "mixer_torque_M1": 2.1146,
          "mixer_torque_M2": 2.1523
     },
     "38": {
          "Time": "11:21:35.049",
          "mixer_motor_temperature_M1": 14.5,
          "mixer_motor_temperature_M2": 17.5,
          "mixer_speed_M1": 20.3462,
          "mixer_speed_M2": 20.3382,
          "mixer_torque_M1": 2.7565,
          "mixer_torque_M2": 2.832
     },
     "39": {
          "Time": "11:21:35.809",
          "mixer_motor_temperature_M1": 15.0,
          "mixer_motor_temperature_M2": 17.5,
          "mixer_speed_M1": 20.7226,
          "mixer_speed_M2": 20.454,
          "mixer_torque_M1": 2.4166,
          "mixer_torque_M2": 2.8698
     },
     "40": {
          "Time": "11:21:36.571",
          "mixer_motor_temperature_M1": 14.5,
          "mixer_motor_temperature_M2": 17.5,
          "mixer_speed_M1": 20.3918,
          "mixer_speed_M2": 20.3872,
          "mixer_torque_M1": 1.9635,
          "mixer_torque_M2": 3.1718
     },
     "41": {
          "Time": "11:21:37.330",
          "mixer_motor_temperature_M1": 14.1,
          "mixer_motor_temperature_M2": 17.5,
          "mixer_speed_M1": 20.2562,
          "mixer_speed_M2": 20.3041,
          "mixer_torque_M1": 2.2656,
          "mixer_torque_M2": 2.681
     },
     "42": {
          "Time": "11:21:38.091",
          "mixer_motor_temperature_M1": 14.5,
          "mixer_motor_temperature_M2": 17.7,
          "mixer_speed_M1": 20.2171,
          "mixer_speed_M2": 20.3479,
          "mixer_torque_M1": 2.7942,
          "mixer_torque_M2": 2.3411
     },
     "43": {
          "Time": "11:21:38.854",
          "mixer_motor_temperature_M1": 14.8,
          "mixer_motor_temperature_M2": 17.7,
          "mixer_speed_M1": 20.4714,
          "mixer_speed_M2": 20.4628,
          "mixer_torque_M1": 1.888,
          "mixer_torque_M2": 2.2278
     },
     "44": {
          "Time": "11:21:39.612",
          "mixer_motor_temperature_M1": 15.0,
          "mixer_motor_temperature_M2": 17.3,
          "mixer_speed_M1": 20.309,
          "mixer_speed_M2": 20.2241,
          "mixer_torque_M1": 4.1158,
          "mixer_torque_M2": 2.5677
     },
     "45": {
          "Time": "11:21:40.377",
          "mixer_motor_temperature_M1": 15.4,
          "mixer_motor_temperature_M2": 17.5,
          "mixer_speed_M1": 20.4215,
          "mixer_speed_M2": 20.4641,
          "mixer_torque_M1": 2.039,
          "mixer_torque_M2": 2.7565
     },
     "46": {
          "Time": "11:21:41.137",
          "mixer_motor_temperature_M1": 15.2,
          "mixer_motor_temperature_M2": 17.7,
          "mixer_speed_M1": 20.149,
          "mixer_speed_M2": 20.4584,
          "mixer_torque_M1": 3.3606,
          "mixer_torque_M2": 2.5677
     },
     "47": {
          "Time": "11:21:41.900",
          "mixer_motor_temperature_M1": 15.2,
          "mixer_motor_temperature_M2": 17.7,
          "mixer_speed_M1": 39.4535,
          "mixer_speed_M2": 39.3254,
          "mixer_torque_M1": 2.7187,
          "mixer_torque_M2": 2.5677
     },
     "48": {
          "Time": "11:21:42.662",
          "mixer_motor_temperature_M1": 15.0,
          "mixer_motor_temperature_M2": 17.7,
          "mixer_speed_M1": 39.6383,
          "mixer_speed_M2": 39.5142,
          "mixer_torque_M1": 3.1341,
          "mixer_torque_M2": 3.3606
     },
     "49": {
          "Time": "11:21:43.422",
          "mixer_motor_temperature_M1": 14.5,
          "mixer_motor_temperature_M2": 17.7,
          "mixer_speed_M1": 39.5718,
          "mixer_speed_M2": 39.5552,
          "mixer_torque_M1": 2.7565,
          "mixer_torque_M2": 2.4166
     },
     "50": {
          "Time": "11:21:44.183",
          "mixer_motor_temperature_M1": 15.2,
          "mixer_motor_temperature_M2": 17.5,
          "mixer_speed_M1": 39.6181,
          "mixer_speed_M2": 39.7177,
          "mixer_torque_M1": 2.9453,
          "mixer_torque_M2": 3.1341
     },
     "51": {
          "Time": "11:21:44.947",
          "mixer_motor_temperature_M1": 15.2,
          "mixer_motor_temperature_M2": 18.2,
          "mixer_speed_M1": 39.4793,
          "mixer_speed_M2": 39.6681,
          "mixer_torque_M1": 3.3606,
          "mixer_torque_M2": 3.2474
     },
     "52": {
          "Time": "11:21:45.709",
          "mixer_motor_temperature_M1": 15.0,
          "mixer_motor_temperature_M2": 17.5,
          "mixer_speed_M1": 39.7063,
          "mixer_speed_M2": 39.6334,
          "mixer_torque_M1": 3.2474,
          "mixer_torque_M2": 2.5677
     },
     "53": {
          "Time": "11:21:46.464",
          "mixer_motor_temperature_M1": 15.2,
          "mixer_motor_temperature_M2": 17.7,
          "mixer_speed_M1": 39.5533,
          "mixer_speed_M2": 39.6864,
          "mixer_torque_M1": 2.5299,
          "mixer_torque_M2": 2.5677
     },
     "54": {
          "Time": "11:21:47.238",
          "mixer_motor_temperature_M1": 15.0,
          "mixer_motor_temperature_M2": 17.7,
          "mixer_speed_M1": 39.5712,
          "mixer_speed_M2": 39.9002,
          "mixer_torque_M1": 3.4362,
          "mixer_torque_M2": 3.0586
     },
     "55": {
          "Time": "11:21:48.001",
          "mixer_motor_temperature_M1": 14.8,
          "mixer_motor_temperature_M2": 17.0,
          "mixer_speed_M1": 39.5779,
          "mixer_speed_M2": 39.5558,
          "mixer_torque_M1": 2.9453,
          "mixer_torque_M2": 1.8502
     },
     "56": {
          "Time": "11:21:48.762",
          "mixer_motor_temperature_M1": 14.5,
          "mixer_motor_temperature_M2": 17.5,
          "mixer_speed_M1": 39.5482,
          "mixer_speed_M2": 39.2595,
          "mixer_torque_M1": 3.3984,
          "mixer_torque_M2": 3.4362
     },
     "57": {
          "Time": "11:21:49.524",
          "mixer_motor_temperature_M1": 15.0,
          "mixer_motor_temperature_M2": 17.7,
          "mixer_speed_M1": 39.5484,
          "mixer_speed_M2": 39.6109,
          "mixer_torque_M1": 2.8698,
          "mixer_torque_M2": 2.3034
     },
     "58": {
          "Time": "11:21:50.302",
          "mixer_motor_temperature_M1": 15.0,
          "mixer_motor_temperature_M2": 17.9,
          "mixer_speed_M1": 39.6293,
          "mixer_speed_M2": 40.0732,
          "mixer_torque_M1": 4.0403,
          "mixer_torque_M2": 2.5677
     },
     "59": {
          "Time": "11:21:51.062",
          "mixer_motor_temperature_M1": 15.2,
          "mixer_motor_temperature_M2": 18.2,
          "mixer_speed_M1": 39.8407,
          "mixer_speed_M2": 39.4152,
          "mixer_torque_M1": 3.2474,
          "mixer_torque_M2": 2.1523
     },
     "60": {
          "Time": "11:21:51.830",
          "mixer_motor_temperature_M1": 14.5,
          "mixer_motor_temperature_M2": 17.5,
          "mixer_speed_M1": 39.5821,
          "mixer_speed_M2": 39.2702,
          "mixer_torque_M1": 2.8698,
          "mixer_torque_M2": 2.5677
     },
     "61": {
          "Time": "11:21:52.595",
          "mixer_motor_temperature_M1": 15.0,
          "mixer_motor_temperature_M2": 17.7,
          "mixer_speed_M1": 39.4626,
          "mixer_speed_M2": 39.3715,
          "mixer_torque_M1": 2.5677,
          "mixer_torque_M2": 2.1523
     },
     "62": {
          "Time": "11:21:53.360",
          "mixer_motor_temperature_M1": 15.0,
          "mixer_motor_temperature_M2": 17.9,
          "mixer_speed_M1": 39.6601,
          "mixer_speed_M2": 39.521,
          "mixer_torque_M1": 2.9075,
          "mixer_torque_M2": 3.776
     },
     "63": {
          "Time": "11:21:54.123",
          "mixer_motor_temperature_M1": 14.5,
          "mixer_motor_temperature_M2": 17.5,
          "mixer_speed_M1": 39.5998,
          "mixer_speed_M2": 39.5327,
          "mixer_torque_M1": 2.983,
          "mixer_torque_M2": 2.1523
     },
     "64": {
          "Time": "11:21:54.886",
          "mixer_motor_temperature_M1": 15.4,
          "mixer_motor_temperature_M2": 17.3,
          "mixer_speed_M1": 39.7963,
          "mixer_speed_M2": 39.1712,
          "mixer_torque_M1": 2.983,
          "mixer_torque_M2": 2.7565
     },
     "65": {
          "Time": "11:21:55.648",
          "mixer_motor_temperature_M1": 14.8,
          "mixer_motor_temperature_M2": 17.5,
          "mixer_speed_M1": 39.7566,
          "mixer_speed_M2": 39.6991,
          "mixer_torque_M1": 2.5677,
          "mixer_torque_M2": 2.7565
     },
     "66": {
          "Time": "11:21:56.412",
          "mixer_motor_temperature_M1": 15.2,
          "mixer_motor_temperature_M2": 17.7,
          "mixer_speed_M1": 51.4214,
          "mixer_speed_M2": 60.7299,
          "mixer_torque_M1": 3.2474,
          "mixer_torque_M2": 4.4557
     },
     "67": {
          "Time": "11:21:57.172",
          "mixer_motor_temperature_M1": 15.2,
          "mixer_motor_temperature_M2": 17.5,
          "mixer_speed_M1": 59.551,
          "mixer_speed_M2": 60.1469,
          "mixer_torque_M1": 4.0781,
          "mixer_torque_M2": 3.5117
     },
     "68": {
          "Time": "11:21:57.960",
          "mixer_motor_temperature_M1": 15.2,
          "mixer_motor_temperature_M2": 17.3,
          "mixer_speed_M1": 59.4971,
          "mixer_speed_M2": 59.9253,
          "mixer_torque_M1": 2.7187,
          "mixer_torque_M2": 3.0963
     },
     "69": {
          "Time": "11:21:58.721",
          "mixer_motor_temperature_M1": 14.3,
          "mixer_motor_temperature_M2": 17.7,
          "mixer_speed_M1": 60.1146,
          "mixer_speed_M2": 59.814,
          "mixer_torque_M1": 2.7187,
          "mixer_torque_M2": 2.8698
     },
     "70": {
          "Time": "11:21:59.480",
          "mixer_motor_temperature_M1": 14.5,
          "mixer_motor_temperature_M2": 17.5,
          "mixer_speed_M1": 60.1739,
          "mixer_speed_M2": 60.2671,
          "mixer_torque_M1": 2.7187,
          "mixer_torque_M2": 2.983
     },
     "71": {
          "Time": "11:22:00.243",
          "mixer_motor_temperature_M1": 14.1,
          "mixer_motor_temperature_M2": 17.5,
          "mixer_speed_M1": 59.9486,
          "mixer_speed_M2": 59.7521,
          "mixer_torque_M1": 4.0026,
          "mixer_torque_M2": 3.8515
     },
     "72": {
          "Time": "11:22:00.993",
          "mixer_motor_temperature_M1": 14.5,
          "mixer_motor_temperature_M2": 17.5,
          "mixer_speed_M1": 60.0159,
          "mixer_speed_M2": 59.9164,
          "mixer_torque_M1": 3.2096,
          "mixer_torque_M2": 4.6067
     },
     "73": {
          "Time": "11:22:01.753",
          "mixer_motor_temperature_M1": 14.5,
          "mixer_motor_temperature_M2": 17.5,
          "mixer_speed_M1": 60.041,
          "mixer_speed_M2": 59.8344,
          "mixer_torque_M1": 3.1718,
          "mixer_torque_M2": 2.4922
     },
     "74": {
          "Time": "11:22:02.515",
          "mixer_motor_temperature_M1": 14.8,
          "mixer_motor_temperature_M2": 17.7,
          "mixer_speed_M1": 60.067,
          "mixer_speed_M2": 60.2612,
          "mixer_torque_M1": 2.983,
          "mixer_torque_M2": 3.8893
     },
     "75": {
          "Time": "11:22:03.293",
          "mixer_motor_temperature_M1": 15.0,
          "mixer_motor_temperature_M2": 17.7,
          "mixer_speed_M1": 59.7612,
          "mixer_speed_M2": 59.9888,
          "mixer_torque_M1": 3.6627,
          "mixer_torque_M2": 4.1914
     },
     "76": {
          "Time": "11:22:04.049",
          "mixer_motor_temperature_M1": 14.3,
          "mixer_motor_temperature_M2": 17.5,
          "mixer_speed_M1": 59.9865,
          "mixer_speed_M2": 60.3607,
          "mixer_torque_M1": 3.8893,
          "mixer_torque_M2": 4.0026
     },
     "77": {
          "Time": "11:22:04.810",
          "mixer_motor_temperature_M1": 15.2,
          "mixer_motor_temperature_M2": 17.5,
          "mixer_speed_M1": 59.9393,
          "mixer_speed_M2": 60.0066,
          "mixer_torque_M1": 3.4362,
          "mixer_torque_M2": 2.8698
     },
     "78": {
          "Time": "11:22:05.572",
          "mixer_motor_temperature_M1": 14.5,
          "mixer_motor_temperature_M2": 17.5,
          "mixer_speed_M1": 60.4529,
          "mixer_speed_M2": 59.5307,
          "mixer_torque_M1": 2.6432,
          "mixer_torque_M2": 3.2096
     },
     "79": {
          "Time": "11:22:06.329",
          "mixer_motor_temperature_M1": 15.0,
          "mixer_motor_temperature_M2": 17.5,
          "mixer_speed_M1": 59.9293,
          "mixer_speed_M2": 60.1066,
          "mixer_torque_M1": 3.3984,
          "mixer_torque_M2": 3.4739
     },
     "80": {
          "Time": "11:22:07.109",
          "mixer_motor_temperature_M1": 15.0,
          "mixer_motor_temperature_M2": 17.5,
          "mixer_speed_M1": 59.7894,
          "mixer_speed_M2": 59.8536,
          "mixer_torque_M1": 3.3229,
          "mixer_torque_M2": 2.983
     },
     "81": {
          "Time": "11:22:07.871",
          "mixer_motor_temperature_M1": 15.0,
          "mixer_motor_temperature_M2": 17.5,
          "mixer_speed_M1": 60.0587,
          "mixer_speed_M2": 60.1358,
          "mixer_torque_M1": 3.1718,
          "mixer_torque_M2": 3.0586
     },
     "82": {
          "Time": "11:22:08.635",
          "mixer_motor_temperature_M1": 14.3,
          "mixer_motor_temperature_M2": 17.7,
          "mixer_speed_M1": 59.8022,
          "mixer_speed_M2": 60.0966,
          "mixer_torque_M1": 3.1341,
          "mixer_torque_M2": 3.4739
     },
     "83": {
          "Time": "11:22:09.382",
          "mixer_motor_temperature_M1": 15.0,
          "mixer_motor_temperature_M2": 17.5,
          "mixer_speed_M1": 59.9886,
          "mixer_speed_M2": 60.2482,
          "mixer_torque_M1": 2.9075,
          "mixer_torque_M2": 3.776
     },
     "84": {
          "Time": "11:22:10.146",
          "mixer_motor_temperature_M1": 14.5,
          "mixer_motor_temperature_M2": 18.2,
          "mixer_speed_M1": 59.6996,
          "mixer_speed_M2": 60.4811,
          "mixer_torque_M1": 4.1914,
          "mixer_torque_M2": 3.8138
     },
     "85": {
          "Time": "11:22:10.907",
          "mixer_motor_temperature_M1": 14.8,
          "mixer_motor_temperature_M2": 17.5,
          "mixer_speed_M1": 59.4682,
          "mixer_speed_M2": 59.9852,
          "mixer_torque_M1": 3.2474,
          "mixer_torque_M2": 3.8138
     },
     "86": {
          "Time": "11:22:11.674",
          "mixer_motor_temperature_M1": 14.8,
          "mixer_motor_temperature_M2": 17.9,
          "mixer_speed_M1": 80.2576,
          "mixer_speed_M2": 80.2538,
          "mixer_torque_M1": 4.6067,
          "mixer_torque_M2": 3.1718
     },
     "87": {
          "Time": "11:22:12.432",
          "mixer_motor_temperature_M1": 14.1,
          "mixer_motor_temperature_M2": 17.9,
          "mixer_speed_M1": 80.2275,
          "mixer_speed_M2": 80.2381,
          "mixer_torque_M1": 3.3606,
          "mixer_torque_M2": 4.4934
     },
     "88": {
          "Time": "11:22:13.194",
          "mixer_motor_temperature_M1": 15.2,
          "mixer_motor_temperature_M2": 17.7,
          "mixer_speed_M1": 80.4124,
          "mixer_speed_M2": 80.1236,
          "mixer_torque_M1": 3.7382,
          "mixer_torque_M2": 3.6627
     },
     "89": {
          "Time": "11:22:13.957",
          "mixer_motor_temperature_M1": 14.3,
          "mixer_motor_temperature_M2": 17.7,
          "mixer_speed_M1": 80.3819,
          "mixer_speed_M2": 80.4395,
          "mixer_torque_M1": 3.4362,
          "mixer_torque_M2": 3.8138
     },
     "90": {
          "Time": "11:22:14.716",
          "mixer_motor_temperature_M1": 15.0,
          "mixer_motor_temperature_M2": 17.5,
          "mixer_speed_M1": 80.1901,
          "mixer_speed_M2": 80.4098,
          "mixer_torque_M1": 4.1536,
          "mixer_torque_M2": 4.0781
     },
     "91": {
          "Time": "11:22:15.480",
          "mixer_motor_temperature_M1": 15.2,
          "mixer_motor_temperature_M2": 17.9,
          "mixer_speed_M1": 80.1301,
          "mixer_speed_M2": 80.283,
          "mixer_torque_M1": 3.1341,
          "mixer_torque_M2": 4.8333
     },
     "92": {
          "Time": "11:22:16.246",
          "mixer_motor_temperature_M1": 15.0,
          "mixer_motor_temperature_M2": 17.7,
          "mixer_speed_M1": 80.2757,
          "mixer_speed_M2": 80.5918,
          "mixer_torque_M1": 3.8138,
          "mixer_torque_M2": 4.4934
     },
     "93": {
          "Time": "11:22:17.022",
          "mixer_motor_temperature_M1": 14.5,
          "mixer_motor_temperature_M2": 17.9,
          "mixer_speed_M1": 80.2773,
          "mixer_speed_M2": 80.5463,
          "mixer_torque_M1": 3.4362,
          "mixer_torque_M2": 4.0403
     },
     "94": {
          "Time": "11:22:17.785",
          "mixer_motor_temperature_M1": 14.3,
          "mixer_motor_temperature_M2": 17.5,
          "mixer_speed_M1": 80.2519,
          "mixer_speed_M2": 80.039,
          "mixer_torque_M1": 3.7005,
          "mixer_torque_M2": 4.2669
     },
     "95": {
          "Time": "11:22:18.546",
          "mixer_motor_temperature_M1": 15.0,
          "mixer_motor_temperature_M2": 17.9,
          "mixer_speed_M1": 80.3237,
          "mixer_speed_M2": 80.4067,
          "mixer_torque_M1": 4.2291,
          "mixer_torque_M2": 4.2669
     },
     "96": {
          "Time": "11:22:19.323",
          "mixer_motor_temperature_M1": 14.8,
          "mixer_motor_temperature_M2": 17.9,
          "mixer_speed_M1": 80.2012,
          "mixer_speed_M2": 80.3223,
          "mixer_torque_M1": 3.7382,
          "mixer_torque_M2": 4.3046
     },
     "97": {
          "Time": "11:22:20.083",
          "mixer_motor_temperature_M1": 14.5,
          "mixer_motor_temperature_M2": 18.2,
          "mixer_speed_M1": 80.4954,
          "mixer_speed_M2": 80.1434,
          "mixer_torque_M1": 4.3424,
          "mixer_torque_M2": 4.7955
     },
     "98": {
          "Time": "11:22:20.846",
          "mixer_motor_temperature_M1": 14.8,
          "mixer_motor_temperature_M2": 17.5,
          "mixer_speed_M1": 80.4568,
          "mixer_speed_M2": 80.0596,
          "mixer_torque_M1": 4.4557,
          "mixer_torque_M2": 4.1914
     },
     "99": {
          "Time": "11:22:21.609",
          "mixer_motor_temperature_M1": 14.1,
          "mixer_motor_temperature_M2": 18.2,
          "mixer_speed_M1": 80.8221,
          "mixer_speed_M2": 80.3481,
          "mixer_torque_M1": 4.0781,
          "mixer_torque_M2": 4.1158
     },
     "100": {
          "Time": "11:22:22.365",
          "mixer_motor_temperature_M1": 14.1,
          "mixer_motor_temperature_M2": 17.7,
          "mixer_speed_M1": 80.5972,
          "mixer_speed_M2": 80.005,
          "mixer_torque_M1": 3.7005,
          "mixer_torque_M2": 4.2669
     },
     "101": {
          "Time": "11:22:23.122",
          "mixer_motor_temperature_M1": 14.8,
          "mixer_motor_temperature_M2": 17.7,
          "mixer_speed_M1": 80.1965,
          "mixer_speed_M2": 80.6852,
          "mixer_torque_M1": 4.871,
          "mixer_torque_M2": 3.5872
     },
     "102": {
          "Time": "11:22:23.884",
          "mixer_motor_temperature_M1": 14.5,
          "mixer_motor_temperature_M2": 17.5,
          "mixer_speed_M1": 80.683,
          "mixer_speed_M2": 80.5128,
          "mixer_torque_M1": 4.0403,
          "mixer_torque_M2": 4.3046
     },
     "103": {
          "Time": "11:22:24.643",
          "mixer_motor_temperature_M1": 15.0,
          "mixer_motor_temperature_M2": 17.5,
          "mixer_speed_M1": 80.3012,
          "mixer_speed_M2": 80.3525,
          "mixer_torque_M1": 4.3802,
          "mixer_torque_M2": 4.72
     },
     "104": {
          "Time": "11:22:25.405",
          "mixer_motor_temperature_M1": 14.3,
          "mixer_motor_temperature_M2": 17.5,
          "mixer_speed_M1": 80.1604,
          "mixer_speed_M2": 80.2664,
          "mixer_torque_M1": 4.4557,
          "mixer_torque_M2": 3.5872
     },
     "105": {
          "Time": "11:22:26.168",
          "mixer_motor_temperature_M1": 14.5,
          "mixer_motor_temperature_M2": 17.9,
          "mixer_speed_M1": 79.9042,
          "mixer_speed_M2": 80.6888,
          "mixer_torque_M1": 4.2669,
          "mixer_torque_M2": 3.7382
     },
     "106": {
          "Time": "11:22:26.928",
          "mixer_motor_temperature_M1": 14.5,
          "mixer_motor_temperature_M2": 18.2,
          "mixer_speed_M1": 99.5186,
          "mixer_speed_M2": 99.5511,
          "mixer_torque_M1": 4.1914,
          "mixer_torque_M2": 3.7382
     },
     "107": {
          "Time": "11:22:27.688",
          "mixer_motor_temperature_M1": 14.1,
          "mixer_motor_temperature_M2": 18.2,
          "mixer_speed_M1": 99.4964,
          "mixer_speed_M2": 99.877,
          "mixer_torque_M1": 3.4362,
          "mixer_torque_M2": 3.6627
     },
     "108": {
          "Time": "11:22:28.449",
          "mixer_motor_temperature_M1": 15.0,
          "mixer_motor_temperature_M2": 18.2,
          "mixer_speed_M1": 99.4695,
          "mixer_speed_M2": 99.695,
          "mixer_torque_M1": 4.1914,
          "mixer_torque_M2": 4.7955
     },
     "109": {
          "Time": "11:22:29.214",
          "mixer_motor_temperature_M1": 14.5,
          "mixer_motor_temperature_M2": 17.5,
          "mixer_speed_M1": 99.6329,
          "mixer_speed_M2": 99.444,
          "mixer_torque_M1": 4.7955,
          "mixer_torque_M2": 4.569
     },
     "110": {
          "Time": "11:22:29.984",
          "mixer_motor_temperature_M1": 15.4,
          "mixer_motor_temperature_M2": 17.5,
          "mixer_speed_M1": 99.792,
          "mixer_speed_M2": 99.6268,
          "mixer_torque_M1": 3.3229,
          "mixer_torque_M2": 4.2291
     },
     "111": {
          "Time": "11:22:30.743",
          "mixer_motor_temperature_M1": 15.2,
          "mixer_motor_temperature_M2": 18.2,
          "mixer_speed_M1": 99.7334,
          "mixer_speed_M2": 99.4312,
          "mixer_torque_M1": 3.1718,
          "mixer_torque_M2": 6.2304
     },
     "112": {
          "Time": "11:22:31.505",
          "mixer_motor_temperature_M1": 14.8,
          "mixer_motor_temperature_M2": 17.7,
          "mixer_speed_M1": 98.9196,
          "mixer_speed_M2": 99.4297,
          "mixer_torque_M1": 4.871,
          "mixer_torque_M2": 4.0781
     },
     "113": {
          "Time": "11:22:32.266",
          "mixer_motor_temperature_M1": 15.4,
          "mixer_motor_temperature_M2": 17.7,
          "mixer_speed_M1": 99.5992,
          "mixer_speed_M2": 99.6051,
          "mixer_torque_M1": 4.3424,
          "mixer_torque_M2": 4.0403
     },
     "114": {
          "Time": "11:22:33.028",
          "mixer_motor_temperature_M1": 14.5,
          "mixer_motor_temperature_M2": 17.7,
          "mixer_speed_M1": 99.5149,
          "mixer_speed_M2": 99.6156,
          "mixer_torque_M1": 3.0963,
          "mixer_torque_M2": 4.6067
     },
     "115": {
          "Time": "11:22:33.777",
          "mixer_motor_temperature_M1": 14.8,
          "mixer_motor_temperature_M2": 17.5,
          "mixer_speed_M1": 100.2799,
          "mixer_speed_M2": 99.2592,
          "mixer_torque_M1": 3.2851,
          "mixer_torque_M2": 4.6067
     },
     "116": {
          "Time": "11:22:34.545",
          "mixer_motor_temperature_M1": 15.0,
          "mixer_motor_temperature_M2": 17.7,
          "mixer_speed_M1": 99.7374,
          "mixer_speed_M2": 99.2856,
          "mixer_torque_M1": 4.6445,
          "mixer_torque_M2": 3.8138
     },
     "117": {
          "Time": "11:22:35.301",
          "mixer_motor_temperature_M1": 15.0,
          "mixer_motor_temperature_M2": 18.2,
          "mixer_speed_M1": 99.2212,
          "mixer_speed_M2": 99.6486,
          "mixer_torque_M1": 4.7955,
          "mixer_torque_M2": 3.6627
     },
     "118": {
          "Time": "11:22:36.079",
          "mixer_motor_temperature_M1": 14.8,
          "mixer_motor_temperature_M2": 17.7,
          "mixer_speed_M1": 99.4397,
          "mixer_speed_M2": 100.2203,
          "mixer_torque_M1": 3.2096,
          "mixer_torque_M2": 4.0026
     },
     "119": {
          "Time": "11:22:36.841",
          "mixer_motor_temperature_M1": 15.0,
          "mixer_motor_temperature_M2": 18.2,
          "mixer_speed_M1": 99.4992,
          "mixer_speed_M2": 99.8246,
          "mixer_torque_M1": 3.8893,
          "mixer_torque_M2": 5.3997
     },
     "120": {
          "Time": "11:22:37.588",
          "mixer_motor_temperature_M1": 14.5,
          "mixer_motor_temperature_M2": 17.5,
          "mixer_speed_M1": 99.2454,
          "mixer_speed_M2": 99.7275,
          "mixer_torque_M1": 4.6822,
          "mixer_torque_M2": 3.8138
     },
     "121": {
          "Time": "11:22:38.363",
          "mixer_motor_temperature_M1": 14.5,
          "mixer_motor_temperature_M2": 17.9,
          "mixer_speed_M1": 100.068,
          "mixer_speed_M2": 99.8286,
          "mixer_torque_M1": 4.4934,
          "mixer_torque_M2": 4.0403
     },
     "122": {
          "Time": "11:22:39.126",
          "mixer_motor_temperature_M1": 14.1,
          "mixer_motor_temperature_M2": 17.7,
          "mixer_speed_M1": 99.7751,
          "mixer_speed_M2": 99.7061,
          "mixer_torque_M1": 3.5872,
          "mixer_torque_M2": 3.7005
     },
     "123": {
          "Time": "11:22:39.890",
          "mixer_motor_temperature_M1": 14.5,
          "mixer_motor_temperature_M2": 18.2,
          "mixer_speed_M1": 99.3632,
          "mixer_speed_M2": 99.4463,
          "mixer_torque_M1": 4.2669,
          "mixer_torque_M2": 4.72
     },
     "124": {
          "Time": "11:22:40.653",
          "mixer_motor_temperature_M1": 14.5,
          "mixer_motor_temperature_M2": 18.2,
          "mixer_speed_M1": 99.5434,
          "mixer_speed_M2": 99.7746,
          "mixer_torque_M1": 4.1158,
          "mixer_torque_M2": 4.2669
     },
     "125": {
          "Time": "11:22:41.433",
          "mixer_motor_temperature_M1": 15.0,
          "mixer_motor_temperature_M2": 18.2,
          "mixer_speed_M1": 108.642,
          "mixer_speed_M2": 121.0268,
          "mixer_torque_M1": 3.625,
          "mixer_torque_M2": 3.776
     },
     "126": {
          "Time": "11:22:42.192",
          "mixer_motor_temperature_M1": 14.8,
          "mixer_motor_temperature_M2": 18.4,
          "mixer_speed_M1": 119.4766,
          "mixer_speed_M2": 119.8245,
          "mixer_torque_M1": 4.9466,
          "mixer_torque_M2": 5.0221
     },
     "127": {
          "Time": "11:22:42.957",
          "mixer_motor_temperature_M1": 15.0,
          "mixer_motor_temperature_M2": 18.2,
          "mixer_speed_M1": 120.3969,
          "mixer_speed_M2": 119.5497,
          "mixer_torque_M1": 3.7005,
          "mixer_torque_M2": 4.0026
     },
     "128": {
          "Time": "11:22:43.719",
          "mixer_motor_temperature_M1": 14.8,
          "mixer_motor_temperature_M2": 18.2,
          "mixer_speed_M1": 119.9296,
          "mixer_speed_M2": 120.0304,
          "mixer_torque_M1": 5.1731,
          "mixer_torque_M2": 4.0026
     },
     "129": {
          "Time": "11:22:44.482",
          "mixer_motor_temperature_M1": 15.4,
          "mixer_motor_temperature_M2": 18.2,
          "mixer_speed_M1": 120.608,
          "mixer_speed_M2": 120.3984,
          "mixer_torque_M1": 4.1536,
          "mixer_torque_M2": 4.0026
     },
     "130": {
          "Time": "11:22:45.259",
          "mixer_motor_temperature_M1": 15.0,
          "mixer_motor_temperature_M2": 18.2,
          "mixer_speed_M1": 120.0967,
          "mixer_speed_M2": 120.1683,
          "mixer_torque_M1": 4.4934,
          "mixer_torque_M2": 5.6262
     },
     "131": {
          "Time": "11:22:46.022",
          "mixer_motor_temperature_M1": 15.0,
          "mixer_motor_temperature_M2": 17.9,
          "mixer_speed_M1": 120.1954,
          "mixer_speed_M2": 119.8647,
          "mixer_torque_M1": 4.1536,
          "mixer_torque_M2": 4.4934
     },
     "132": {
          "Time": "11:22:46.782",
          "mixer_motor_temperature_M1": 15.0,
          "mixer_motor_temperature_M2": 18.2,
          "mixer_speed_M1": 119.3648,
          "mixer_speed_M2": 120.2757,
          "mixer_torque_M1": 4.9466,
          "mixer_torque_M2": 4.2669
     },
     "133": {
          "Time": "11:22:47.545",
          "mixer_motor_temperature_M1": 14.8,
          "mixer_motor_temperature_M2": 18.2,
          "mixer_speed_M1": 119.7907,
          "mixer_speed_M2": 119.7986,
          "mixer_torque_M1": 4.1536,
          "mixer_torque_M2": 4.8333
     },
     "134": {
          "Time": "11:22:48.319",
          "mixer_motor_temperature_M1": 14.5,
          "mixer_motor_temperature_M2": 18.2,
          "mixer_speed_M1": 119.9127,
          "mixer_speed_M2": 119.6003,
          "mixer_torque_M1": 4.3802,
          "mixer_torque_M2": 4.7578
     },
     "135": {
          "Time": "11:22:49.086",
          "mixer_motor_temperature_M1": 15.0,
          "mixer_motor_temperature_M2": 18.2,
          "mixer_speed_M1": 121.5023,
          "mixer_speed_M2": 119.2019,
          "mixer_torque_M1": 3.927,
          "mixer_torque_M2": 4.3802
     },
     "136": {
          "Time": "11:22:49.849",
          "mixer_motor_temperature_M1": 14.8,
          "mixer_motor_temperature_M2": 17.9,
          "mixer_speed_M1": 120.8727,
          "mixer_speed_M2": 118.9582,
          "mixer_torque_M1": 4.7955,
          "mixer_torque_M2": 4.1914
     },
     "137": {
          "Time": "11:22:50.607",
          "mixer_motor_temperature_M1": 15.7,
          "mixer_motor_temperature_M2": 18.4,
          "mixer_speed_M1": 120.0486,
          "mixer_speed_M2": 119.7843,
          "mixer_torque_M1": 4.4557,
          "mixer_torque_M2": 4.1536
     },
     "138": {
          "Time": "11:22:51.366",
          "mixer_motor_temperature_M1": 14.8,
          "mixer_motor_temperature_M2": 17.9,
          "mixer_speed_M1": 119.7561,
          "mixer_speed_M2": 120.2724,
          "mixer_torque_M1": 4.3424,
          "mixer_torque_M2": 4.7578
     },
     "139": {
          "Time": "11:22:52.130",
          "mixer_motor_temperature_M1": 15.0,
          "mixer_motor_temperature_M2": 17.9,
          "mixer_speed_M1": 119.76,
          "mixer_speed_M2": 120.2469,
          "mixer_torque_M1": 4.8333,
          "mixer_torque_M2": 4.9088
     },
     "140": {
          "Time": "11:22:52.894",
          "mixer_motor_temperature_M1": 14.8,
          "mixer_motor_temperature_M2": 17.9,
          "mixer_speed_M1": 119.9127,
          "mixer_speed_M2": 120.1154,
          "mixer_torque_M1": 3.5494,
          "mixer_torque_M2": 4.2291
     },
     "141": {
          "Time": "11:22:53.657",
          "mixer_motor_temperature_M1": 15.4,
          "mixer_motor_temperature_M2": 18.6,
          "mixer_speed_M1": 119.6067,
          "mixer_speed_M2": 120.3876,
          "mixer_torque_M1": 4.1158,
          "mixer_torque_M2": 4.3802
     },
     "142": {
          "Time": "11:22:54.419",
          "mixer_motor_temperature_M1": 14.5,
          "mixer_motor_temperature_M2": 18.4,
          "mixer_speed_M1": 120.0688,
          "mixer_speed_M2": 120.1524,
          "mixer_torque_M1": 4.0781,
          "mixer_torque_M2": 3.4739
     },
     "143": {
          "Time": "11:22:55.180",
          "mixer_motor_temperature_M1": 15.2,
          "mixer_motor_temperature_M2": 18.4,
          "mixer_speed_M1": 119.4508,
          "mixer_speed_M2": 119.9321,
          "mixer_torque_M1": 4.5312,
          "mixer_torque_M2": 4.8333
     },
     "144": {
          "Time": "11:22:55.961",
          "mixer_motor_temperature_M1": 15.4,
          "mixer_motor_temperature_M2": 18.2,
          "mixer_speed_M1": 120.4025,
          "mixer_speed_M2": 119.9961,
          "mixer_torque_M1": 4.0403,
          "mixer_torque_M2": 3.7005
     },
     "145": {
          "Time": "11:22:56.722",
          "mixer_motor_temperature_M1": 15.0,
          "mixer_motor_temperature_M2": 18.2,
          "mixer_speed_M1": 99.2862,
          "mixer_speed_M2": 99.5585,
          "mixer_torque_M1": 3.7382,
          "mixer_torque_M2": 4.0781
     },
     "146": {
          "Time": "11:22:57.480",
          "mixer_motor_temperature_M1": 15.0,
          "mixer_motor_temperature_M2": 18.2,
          "mixer_speed_M1": 99.1661,
          "mixer_speed_M2": 100.1585,
          "mixer_torque_M1": 4.871,
          "mixer_torque_M2": 5.3619
     },
     "147": {
          "Time": "11:22:58.241",
          "mixer_motor_temperature_M1": 14.5,
          "mixer_motor_temperature_M2": 18.6,
          "mixer_speed_M1": 99.8173,
          "mixer_speed_M2": 99.6667,
          "mixer_torque_M1": 3.0963,
          "mixer_torque_M2": 4.3046
     },
     "148": {
          "Time": "11:22:59.004",
          "mixer_motor_temperature_M1": 15.0,
          "mixer_motor_temperature_M2": 18.2,
          "mixer_speed_M1": 99.9503,
          "mixer_speed_M2": 99.4742,
          "mixer_torque_M1": 3.1341,
          "mixer_torque_M2": 4.1536
     },
     "149": {
          "Time": "11:22:59.766",
          "mixer_motor_temperature_M1": 15.2,
          "mixer_motor_temperature_M2": 18.2,
          "mixer_speed_M1": 99.528,
          "mixer_speed_M2": 99.3538,
          "mixer_torque_M1": 4.3802,
          "mixer_torque_M2": 4.2669
     },
     "150": {
          "Time": "11:23:00.528",
          "mixer_motor_temperature_M1": 15.2,
          "mixer_motor_temperature_M2": 17.9,
          "mixer_speed_M1": 99.8848,
          "mixer_speed_M2": 99.4973,
          "mixer_torque_M1": 4.3424,
          "mixer_torque_M2": 4.0781
     },
     "151": {
          "Time": "11:23:01.290",
          "mixer_motor_temperature_M1": 14.8,
          "mixer_motor_temperature_M2": 18.2,
          "mixer_speed_M1": 98.9215,
          "mixer_speed_M2": 99.3488,
          "mixer_torque_M1": 2.6432,
          "mixer_torque_M2": 3.625
     },
     "152": {
          "Time": "11:23:02.050",
          "mixer_motor_temperature_M1": 15.0,
          "mixer_motor_temperature_M2": 18.2,
          "mixer_speed_M1": 99.9764,
          "mixer_speed_M2": 99.3239,
          "mixer_torque_M1": 3.5494,
          "mixer_torque_M2": 4.6067
     },
     "153": {
          "Time": "11:23:02.808",
          "mixer_motor_temperature_M1": 15.4,
          "mixer_motor_temperature_M2": 17.9,
          "mixer_speed_M1": 99.6323,
          "mixer_speed_M2": 99.1934,
          "mixer_torque_M1": 3.776,
          "mixer_torque_M2": 5.7773
     },
     "154": {
          "Time": "11:23:03.570",
          "mixer_motor_temperature_M1": 15.2,
          "mixer_motor_temperature_M2": 17.9,
          "mixer_speed_M1": 99.5562,
          "mixer_speed_M2": 99.6417,
          "mixer_torque_M1": 4.1158,
          "mixer_torque_M2": 4.3802
     },
     "155": {
          "Time": "11:23:04.350",
          "mixer_motor_temperature_M1": 15.0,
          "mixer_motor_temperature_M2": 18.4,
          "mixer_speed_M1": 100.3787,
          "mixer_speed_M2": 100.0579,
          "mixer_torque_M1": 3.1718,
          "mixer_torque_M2": 3.8893
     },
     "156": {
          "Time": "11:23:05.110",
          "mixer_motor_temperature_M1": 15.0,
          "mixer_motor_temperature_M2": 18.2,
          "mixer_speed_M1": 99.5596,
          "mixer_speed_M2": 100.2092,
          "mixer_torque_M1": 4.0781,
          "mixer_torque_M2": 4.6067
     },
     "157": {
          "Time": "11:23:05.867",
          "mixer_motor_temperature_M1": 14.5,
          "mixer_motor_temperature_M2": 18.6,
          "mixer_speed_M1": 99.9866,
          "mixer_speed_M2": 99.5157,
          "mixer_torque_M1": 4.6822,
          "mixer_torque_M2": 3.6627
     },
     "158": {
          "Time": "11:23:06.629",
          "mixer_motor_temperature_M1": 14.8,
          "mixer_motor_temperature_M2": 18.2,
          "mixer_speed_M1": 99.0707,
          "mixer_speed_M2": 99.6292,
          "mixer_torque_M1": 3.8138,
          "mixer_torque_M2": 3.8515
     },
     "159": {
          "Time": "11:23:07.389",
          "mixer_motor_temperature_M1": 15.0,
          "mixer_motor_temperature_M2": 18.2,
          "mixer_speed_M1": 99.275,
          "mixer_speed_M2": 99.6519,
          "mixer_torque_M1": 3.7005,
          "mixer_torque_M2": 3.4362
     },
     "160": {
          "Time": "11:23:08.153",
          "mixer_motor_temperature_M1": 15.4,
          "mixer_motor_temperature_M2": 18.2,
          "mixer_speed_M1": 99.2745,
          "mixer_speed_M2": 99.7638,
          "mixer_torque_M1": 3.5494,
          "mixer_torque_M2": 4.0781
     },
     "161": {
          "Time": "11:23:08.931",
          "mixer_motor_temperature_M1": 15.4,
          "mixer_motor_temperature_M2": 18.6,
          "mixer_speed_M1": 99.5581,
          "mixer_speed_M2": 99.0835,
          "mixer_torque_M1": 3.7005,
          "mixer_torque_M2": 4.3046
     },
     "162": {
          "Time": "11:23:09.694",
          "mixer_motor_temperature_M1": 14.8,
          "mixer_motor_temperature_M2": 18.2,
          "mixer_speed_M1": 99.6279,
          "mixer_speed_M2": 99.7205,
          "mixer_torque_M1": 3.0586,
          "mixer_torque_M2": 4.0403
     },
     "163": {
          "Time": "11:23:10.448",
          "mixer_motor_temperature_M1": 15.0,
          "mixer_motor_temperature_M2": 18.2,
          "mixer_speed_M1": 99.8517,
          "mixer_speed_M2": 99.012,
          "mixer_torque_M1": 4.569,
          "mixer_torque_M2": 4.2291
     },
     "164": {
          "Time": "11:23:11.212",
          "mixer_motor_temperature_M1": 15.4,
          "mixer_motor_temperature_M2": 18.6,
          "mixer_speed_M1": 99.766,
          "mixer_speed_M2": 99.6489,
          "mixer_torque_M1": 4.2291,
          "mixer_torque_M2": 3.776
     },
     "165": {
          "Time": "11:23:11.975",
          "mixer_motor_temperature_M1": 14.8,
          "mixer_motor_temperature_M2": 18.6,
          "mixer_speed_M1": 80.4492,
          "mixer_speed_M2": 80.6423,
          "mixer_torque_M1": 3.5117,
          "mixer_torque_M2": 4.8333
     },
     "166": {
          "Time": "11:23:12.738",
          "mixer_motor_temperature_M1": 15.0,
          "mixer_motor_temperature_M2": 18.2,
          "mixer_speed_M1": 79.8681,
          "mixer_speed_M2": 80.3229,
          "mixer_torque_M1": 3.927,
          "mixer_torque_M2": 3.6627
     },
     "167": {
          "Time": "11:23:13.517",
          "mixer_motor_temperature_M1": 14.5,
          "mixer_motor_temperature_M2": 18.6,
          "mixer_speed_M1": 80.1592,
          "mixer_speed_M2": 80.2782,
          "mixer_torque_M1": 3.5494,
          "mixer_torque_M2": 3.6627
     },
     "168": {
          "Time": "11:23:14.273",
          "mixer_motor_temperature_M1": 15.0,
          "mixer_motor_temperature_M2": 18.4,
          "mixer_speed_M1": 80.1026,
          "mixer_speed_M2": 80.0724,
          "mixer_torque_M1": 4.3424,
          "mixer_torque_M2": 4.0403
     },
     "169": {
          "Time": "11:23:15.053",
          "mixer_motor_temperature_M1": 15.4,
          "mixer_motor_temperature_M2": 18.4,
          "mixer_speed_M1": 78.8572,
          "mixer_speed_M2": 80.2607,
          "mixer_torque_M1": 4.2669,
          "mixer_torque_M2": 3.1341
     },
     "170": {
          "Time": "11:23:15.820",
          "mixer_motor_temperature_M1": 15.2,
          "mixer_motor_temperature_M2": 18.2,
          "mixer_speed_M1": 80.5043,
          "mixer_speed_M2": 80.3988,
          "mixer_torque_M1": 3.8515,
          "mixer_torque_M2": 3.3984
     },
     "171": {
          "Time": "11:23:16.583",
          "mixer_motor_temperature_M1": 15.0,
          "mixer_motor_temperature_M2": 18.2,
          "mixer_speed_M1": 80.2286,
          "mixer_speed_M2": 80.4842,
          "mixer_torque_M1": 3.5117,
          "mixer_torque_M2": 4.871
     },
     "172": {
          "Time": "11:23:17.340",
          "mixer_motor_temperature_M1": 15.4,
          "mixer_motor_temperature_M2": 18.2,
          "mixer_speed_M1": 80.1035,
          "mixer_speed_M2": 80.302,
          "mixer_torque_M1": 3.4739,
          "mixer_torque_M2": 3.8138
     },
     "173": {
          "Time": "11:23:18.107",
          "mixer_motor_temperature_M1": 15.4,
          "mixer_motor_temperature_M2": 18.2,
          "mixer_speed_M1": 80.3091,
          "mixer_speed_M2": 80.5494,
          "mixer_torque_M1": 3.8515,
          "mixer_torque_M2": 6.4947
     },
     "174": {
          "Time": "11:23:18.898",
          "mixer_motor_temperature_M1": 15.0,
          "mixer_motor_temperature_M2": 18.6,
          "mixer_speed_M1": 80.4378,
          "mixer_speed_M2": 79.7749,
          "mixer_torque_M1": 3.5117,
          "mixer_torque_M2": 3.9648
     },
     "175": {
          "Time": "11:23:19.663",
          "mixer_motor_temperature_M1": 14.5,
          "mixer_motor_temperature_M2": 18.2,
          "mixer_speed_M1": 80.4151,
          "mixer_speed_M2": 80.8911,
          "mixer_torque_M1": 3.5872,
          "mixer_torque_M2": 3.776
     },
     "176": {
          "Time": "11:23:20.430",
          "mixer_motor_temperature_M1": 15.4,
          "mixer_motor_temperature_M2": 18.2,
          "mixer_speed_M1": 80.4682,
          "mixer_speed_M2": 80.5697,
          "mixer_torque_M1": 3.0963,
          "mixer_torque_M2": 4.7955
     },
     "177": {
          "Time": "11:23:21.186",
          "mixer_motor_temperature_M1": 15.4,
          "mixer_motor_temperature_M2": 18.4,
          "mixer_speed_M1": 80.4491,
          "mixer_speed_M2": 80.3523,
          "mixer_torque_M1": 3.6627,
          "mixer_torque_M2": 4.6445
     },
     "178": {
          "Time": "11:23:21.947",
          "mixer_motor_temperature_M1": 14.8,
          "mixer_motor_temperature_M2": 18.2,
          "mixer_speed_M1": 80.3015,
          "mixer_speed_M2": 80.2477,
          "mixer_torque_M1": 3.1718,
          "mixer_torque_M2": 3.3984
     },
     "179": {
          "Time": "11:23:22.707",
          "mixer_motor_temperature_M1": 15.2,
          "mixer_motor_temperature_M2": 18.4,
          "mixer_speed_M1": 80.5495,
          "mixer_speed_M2": 81.5251,
          "mixer_torque_M1": 3.5117,
          "mixer_torque_M2": 3.625
     },
     "180": {
          "Time": "11:23:23.483",
          "mixer_motor_temperature_M1": 14.8,
          "mixer_motor_temperature_M2": 17.9,
          "mixer_speed_M1": 80.9916,
          "mixer_speed_M2": 80.3789,
          "mixer_torque_M1": 3.3606,
          "mixer_torque_M2": 3.7005
     },
     "181": {
          "Time": "11:23:24.261",
          "mixer_motor_temperature_M1": 15.0,
          "mixer_motor_temperature_M2": 18.2,
          "mixer_speed_M1": 80.2566,
          "mixer_speed_M2": 80.8147,
          "mixer_torque_M1": 2.4922,
          "mixer_torque_M2": 3.6627
     },
     "182": {
          "Time": "11:23:25.023",
          "mixer_motor_temperature_M1": 14.5,
          "mixer_motor_temperature_M2": 18.6,
          "mixer_speed_M1": 79.8271,
          "mixer_speed_M2": 81.2301,
          "mixer_torque_M1": 2.832,
          "mixer_torque_M2": 3.5872
     },
     "183": {
          "Time": "11:23:25.798",
          "mixer_motor_temperature_M1": 15.7,
          "mixer_motor_temperature_M2": 18.2,
          "mixer_speed_M1": 80.1741,
          "mixer_speed_M2": 80.447,
          "mixer_torque_M1": 3.6627,
          "mixer_torque_M2": 3.3606
     },
     "184": {
          "Time": "11:23:26.557",
          "mixer_motor_temperature_M1": 14.8,
          "mixer_motor_temperature_M2": 18.2,
          "mixer_speed_M1": 59.5769,
          "mixer_speed_M2": 59.9729,
          "mixer_torque_M1": 2.3411,
          "mixer_torque_M2": 3.0963
     },
     "185": {
          "Time": "11:23:27.313",
          "mixer_motor_temperature_M1": 14.5,
          "mixer_motor_temperature_M2": 18.2,
          "mixer_speed_M1": 59.915,
          "mixer_speed_M2": 60.1278,
          "mixer_torque_M1": 3.0586,
          "mixer_torque_M2": 2.983
     },
     "186": {
          "Time": "11:23:28.083",
          "mixer_motor_temperature_M1": 14.8,
          "mixer_motor_temperature_M2": 18.2,
          "mixer_speed_M1": 59.9213,
          "mixer_speed_M2": 59.6359,
          "mixer_torque_M1": 3.7005,
          "mixer_torque_M2": 4.0026
     },
     "187": {
          "Time": "11:23:28.845",
          "mixer_motor_temperature_M1": 15.4,
          "mixer_motor_temperature_M2": 18.2,
          "mixer_speed_M1": 59.9537,
          "mixer_speed_M2": 59.937,
          "mixer_torque_M1": 2.7565,
          "mixer_torque_M2": 2.832
     },
     "188": {
          "Time": "11:23:29.617",
          "mixer_motor_temperature_M1": 15.2,
          "mixer_motor_temperature_M2": 18.2,
          "mixer_speed_M1": 60.2691,
          "mixer_speed_M2": 60.1822,
          "mixer_torque_M1": 2.9453,
          "mixer_torque_M2": 4.4557
     },
     "189": {
          "Time": "11:23:30.380",
          "mixer_motor_temperature_M1": 15.4,
          "mixer_motor_temperature_M2": 18.4,
          "mixer_speed_M1": 59.5316,
          "mixer_speed_M2": 59.9234,
          "mixer_torque_M1": 3.2851,
          "mixer_torque_M2": 3.4739
     },
     "190": {
          "Time": "11:23:31.157",
          "mixer_motor_temperature_M1": 15.0,
          "mixer_motor_temperature_M2": 18.4,
          "mixer_speed_M1": 60.3738,
          "mixer_speed_M2": 59.0738,
          "mixer_torque_M1": 3.3229,
          "mixer_torque_M2": 3.5117
     },
     "191": {
          "Time": "11:23:31.922",
          "mixer_motor_temperature_M1": 15.0,
          "mixer_motor_temperature_M2": 18.8,
          "mixer_speed_M1": 60.0352,
          "mixer_speed_M2": 60.0485,
          "mixer_torque_M1": 3.0586,
          "mixer_torque_M2": 3.0208
     },
     "192": {
          "Time": "11:23:32.678",
          "mixer_motor_temperature_M1": 14.5,
          "mixer_motor_temperature_M2": 18.4,
          "mixer_speed_M1": 60.99,
          "mixer_speed_M2": 59.8866,
          "mixer_torque_M1": 2.2656,
          "mixer_torque_M2": 2.681
     },
     "193": {
          "Time": "11:23:33.446",
          "mixer_motor_temperature_M1": 15.0,
          "mixer_motor_temperature_M2": 18.4,
          "mixer_speed_M1": 59.724,
          "mixer_speed_M2": 61.0231,
          "mixer_torque_M1": 3.2096,
          "mixer_torque_M2": 2.681
     },
     "194": {
          "Time": "11:23:34.206",
          "mixer_motor_temperature_M1": 15.4,
          "mixer_motor_temperature_M2": 18.2,
          "mixer_speed_M1": 60.0713,
          "mixer_speed_M2": 60.0674,
          "mixer_torque_M1": 2.7565,
          "mixer_torque_M2": 3.2851
     },
     "195": {
          "Time": "11:23:34.966",
          "mixer_motor_temperature_M1": 15.2,
          "mixer_motor_temperature_M2": 18.2,
          "mixer_speed_M1": 60.092,
          "mixer_speed_M2": 59.9927,
          "mixer_torque_M1": 3.1341,
          "mixer_torque_M2": 3.3984
     },
     "196": {
          "Time": "11:23:35.732",
          "mixer_motor_temperature_M1": 15.0,
          "mixer_motor_temperature_M2": 18.2,
          "mixer_speed_M1": 59.849,
          "mixer_speed_M2": 59.9689,
          "mixer_torque_M1": 4.0026,
          "mixer_torque_M2": 2.7187
     },
     "197": {
          "Time": "11:23:36.495",
          "mixer_motor_temperature_M1": 14.8,
          "mixer_motor_temperature_M2": 18.2,
          "mixer_speed_M1": 59.9258,
          "mixer_speed_M2": 60.0313,
          "mixer_torque_M1": 3.6627,
          "mixer_torque_M2": 3.3606
     },
     "198": {
          "Time": "11:23:37.256",
          "mixer_motor_temperature_M1": 15.4,
          "mixer_motor_temperature_M2": 18.4,
          "mixer_speed_M1": 59.8982,
          "mixer_speed_M2": 59.9309,
          "mixer_torque_M1": 3.625,
          "mixer_torque_M2": 3.7382
     },
     "199": {
          "Time": "11:23:38.018",
          "mixer_motor_temperature_M1": 15.2,
          "mixer_motor_temperature_M2": 18.6,
          "mixer_speed_M1": 60.2443,
          "mixer_speed_M2": 60.2217,
          "mixer_torque_M1": 3.7382,
          "mixer_torque_M2": 4.1914
     },
     "200": {
          "Time": "11:23:38.782",
          "mixer_motor_temperature_M1": 16.1,
          "mixer_motor_temperature_M2": 18.2,
          "mixer_speed_M1": 59.9095,
          "mixer_speed_M2": 59.6083,
          "mixer_torque_M1": 3.4739,
          "mixer_torque_M2": 2.983
     },
     "201": {
          "Time": "11:23:39.544",
          "mixer_motor_temperature_M1": 15.7,
          "mixer_motor_temperature_M2": 18.2,
          "mixer_speed_M1": 59.8712,
          "mixer_speed_M2": 60.6951,
          "mixer_torque_M1": 2.6054,
          "mixer_torque_M2": 2.8698
     },
     "202": {
          "Time": "11:23:40.303",
          "mixer_motor_temperature_M1": 15.9,
          "mixer_motor_temperature_M2": 18.2,
          "mixer_speed_M1": 60.2153,
          "mixer_speed_M2": 60.1516,
          "mixer_torque_M1": 3.625,
          "mixer_torque_M2": 3.0208
     },
     "203": {
          "Time": "11:23:41.081",
          "mixer_motor_temperature_M1": 15.2,
          "mixer_motor_temperature_M2": 18.2,
          "mixer_speed_M1": 59.9172,
          "mixer_speed_M2": 59.8884,
          "mixer_torque_M1": 3.2851,
          "mixer_torque_M2": 3.0963
     },
     "204": {
          "Time": "11:23:41.842",
          "mixer_motor_temperature_M1": 15.0,
          "mixer_motor_temperature_M2": 18.6,
          "mixer_speed_M1": 39.7862,
          "mixer_speed_M2": 39.6542,
          "mixer_torque_M1": 1.6992,
          "mixer_torque_M2": 2.3789
     },
     "205": {
          "Time": "11:23:42.614",
          "mixer_motor_temperature_M1": 15.4,
          "mixer_motor_temperature_M2": 18.2,
          "mixer_speed_M1": 39.3523,
          "mixer_speed_M2": 39.7177,
          "mixer_torque_M1": 3.3606,
          "mixer_torque_M2": 3.1341
     },
     "206": {
          "Time": "11:23:43.376",
          "mixer_motor_temperature_M1": 15.0,
          "mixer_motor_temperature_M2": 18.6,
          "mixer_speed_M1": 39.6113,
          "mixer_speed_M2": 39.3214,
          "mixer_torque_M1": 2.4166,
          "mixer_torque_M2": 2.832
     },
     "207": {
          "Time": "11:23:44.139",
          "mixer_motor_temperature_M1": 15.2,
          "mixer_motor_temperature_M2": 18.2,
          "mixer_speed_M1": 39.641,
          "mixer_speed_M2": 39.5506,
          "mixer_torque_M1": 2.4544,
          "mixer_torque_M2": 2.8698
     },
     "208": {
          "Time": "11:23:44.914",
          "mixer_motor_temperature_M1": 15.0,
          "mixer_motor_temperature_M2": 18.2,
          "mixer_speed_M1": 39.5987,
          "mixer_speed_M2": 39.5773,
          "mixer_torque_M1": 2.5299,
          "mixer_torque_M2": 2.2656
     },
     "209": {
          "Time": "11:23:45.691",
          "mixer_motor_temperature_M1": 15.2,
          "mixer_motor_temperature_M2": 18.2,
          "mixer_speed_M1": 39.371,
          "mixer_speed_M2": 39.9662,
          "mixer_torque_M1": 3.2474,
          "mixer_torque_M2": 3.1718
     },
     "210": {
          "Time": "11:23:46.452",
          "mixer_motor_temperature_M1": 15.9,
          "mixer_motor_temperature_M2": 18.2,
          "mixer_speed_M1": 39.5791,
          "mixer_speed_M2": 39.6744,
          "mixer_torque_M1": 2.4922,
          "mixer_torque_M2": 2.1523
     },
     "211": {
          "Time": "11:23:47.216",
          "mixer_motor_temperature_M1": 15.2,
          "mixer_motor_temperature_M2": 18.2,
          "mixer_speed_M1": 39.7467,
          "mixer_speed_M2": 39.6375,
          "mixer_torque_M1": 3.1341,
          "mixer_torque_M2": 2.9075
     },
     "212": {
          "Time": "11:23:47.977",
          "mixer_motor_temperature_M1": 15.0,
          "mixer_motor_temperature_M2": 17.9,
          "mixer_speed_M1": 39.1899,
          "mixer_speed_M2": 40.3253,
          "mixer_torque_M1": 2.6432,
          "mixer_torque_M2": 2.3789
     },
     "213": {
          "Time": "11:23:48.733",
          "mixer_motor_temperature_M1": 15.9,
          "mixer_motor_temperature_M2": 18.6,
          "mixer_speed_M1": 39.1882,
          "mixer_speed_M2": 39.4976,
          "mixer_torque_M1": 3.0963,
          "mixer_torque_M2": 2.6054
     },
     "214": {
          "Time": "11:23:49.491",
          "mixer_motor_temperature_M1": 15.4,
          "mixer_motor_temperature_M2": 18.2,
          "mixer_speed_M1": 39.4952,
          "mixer_speed_M2": 39.2237,
          "mixer_torque_M1": 2.1146,
          "mixer_torque_M2": 1.9635
     },
     "215": {
          "Time": "11:23:50.250",
          "mixer_motor_temperature_M1": 15.0,
          "mixer_motor_temperature_M2": 18.6,
          "mixer_speed_M1": 40.0052,
          "mixer_speed_M2": 39.6918,
          "mixer_torque_M1": 2.681,
          "mixer_torque_M2": 3.0963
     },
     "216": {
          "Time": "11:23:51.013",
          "mixer_motor_temperature_M1": 15.4,
          "mixer_motor_temperature_M2": 18.2,
          "mixer_speed_M1": 39.2477,
          "mixer_speed_M2": 39.4228,
          "mixer_torque_M1": 2.5299,
          "mixer_torque_M2": 2.4166
     },
     "217": {
          "Time": "11:23:51.771",
          "mixer_motor_temperature_M1": 15.4,
          "mixer_motor_temperature_M2": 18.6,
          "mixer_speed_M1": 40.2608,
          "mixer_speed_M2": 39.526,
          "mixer_torque_M1": 3.1341,
          "mixer_torque_M2": 2.2656
     },
     "218": {
          "Time": "11:23:52.525",
          "mixer_motor_temperature_M1": 15.2,
          "mixer_motor_temperature_M2": 18.4,
          "mixer_speed_M1": 39.4516,
          "mixer_speed_M2": 39.4998,
          "mixer_torque_M1": 2.6432,
          "mixer_torque_M2": 2.4922
     },
     "219": {
          "Time": "11:23:53.280",
          "mixer_motor_temperature_M1": 15.0,
          "mixer_motor_temperature_M2": 18.8,
          "mixer_speed_M1": 39.4205,
          "mixer_speed_M2": 39.5499,
          "mixer_torque_M1": 2.7942,
          "mixer_torque_M2": 3.1341
     },
     "220": {
          "Time": "11:23:54.057",
          "mixer_motor_temperature_M1": 15.2,
          "mixer_motor_temperature_M2": 18.4,
          "mixer_speed_M1": 39.5989,
          "mixer_speed_M2": 39.659,
          "mixer_torque_M1": 1.9635,
          "mixer_torque_M2": 2.4166
     },
     "221": {
          "Time": "11:23:54.833",
          "mixer_motor_temperature_M1": 15.2,
          "mixer_motor_temperature_M2": 18.2,
          "mixer_speed_M1": 39.6104,
          "mixer_speed_M2": 39.4954,
          "mixer_torque_M1": 2.983,
          "mixer_torque_M2": 3.4739
     },
     "222": {
          "Time": "11:23:55.590",
          "mixer_motor_temperature_M1": 15.4,
          "mixer_motor_temperature_M2": 18.4,
          "mixer_speed_M1": 39.7434,
          "mixer_speed_M2": 39.6026,
          "mixer_torque_M1": 2.1146,
          "mixer_torque_M2": 2.2278
     },
     "223": {
          "Time": "11:23:56.379",
          "mixer_motor_temperature_M1": 15.0,
          "mixer_motor_temperature_M2": 18.4,
          "mixer_speed_M1": 39.6311,
          "mixer_speed_M2": 33.1335,
          "mixer_torque_M1": 3.0963,
          "mixer_torque_M2": 3.3229
     },
     "224": {
          "Time": "11:23:57.174",
          "mixer_motor_temperature_M1": 15.0,
          "mixer_motor_temperature_M2": 17.9,
          "mixer_speed_M1": 20.2687,
          "mixer_speed_M2": 20.4412,
          "mixer_torque_M1": 1.9635,
          "mixer_torque_M2": 3.0963
     },
     "225": {
          "Time": "11:23:57.952",
          "mixer_motor_temperature_M1": 14.8,
          "mixer_motor_temperature_M2": 18.2,
          "mixer_speed_M1": 20.4567,
          "mixer_speed_M2": 20.2689,
          "mixer_torque_M1": 1.6992,
          "mixer_torque_M2": 2.3411
     },
     "226": {
          "Time": "11:23:58.730",
          "mixer_motor_temperature_M1": 15.0,
          "mixer_motor_temperature_M2": 18.2,
          "mixer_speed_M1": 20.2942,
          "mixer_speed_M2": 20.2818,
          "mixer_torque_M1": 2.4166,
          "mixer_torque_M2": 2.6054
     },
     "227": {
          "Time": "11:23:59.494",
          "mixer_motor_temperature_M1": 15.2,
          "mixer_motor_temperature_M2": 18.4,
          "mixer_speed_M1": 20.1713,
          "mixer_speed_M2": 20.6169,
          "mixer_torque_M1": 2.1523,
          "mixer_torque_M2": 3.3229
     },
     "228": {
          "Time": "11:24:00.256",
          "mixer_motor_temperature_M1": 15.4,
          "mixer_motor_temperature_M2": 18.6,
          "mixer_speed_M1": 20.5401,
          "mixer_speed_M2": 20.2225,
          "mixer_torque_M1": 1.7747,
          "mixer_torque_M2": 2.4922
     },
     "229": {
          "Time": "11:24:01.018",
          "mixer_motor_temperature_M1": 15.0,
          "mixer_motor_temperature_M2": 17.7,
          "mixer_speed_M1": 19.908,
          "mixer_speed_M2": 20.5904,
          "mixer_torque_M1": 2.3034,
          "mixer_torque_M2": 1.9635
     },
     "230": {
          "Time": "11:24:01.784",
          "mixer_motor_temperature_M1": 15.0,
          "mixer_motor_temperature_M2": 18.2,
          "mixer_speed_M1": 20.3432,
          "mixer_speed_M2": 20.6517,
          "mixer_torque_M1": 2.3411,
          "mixer_torque_M2": 2.6432
     },
     "231": {
          "Time": "11:24:02.549",
          "mixer_motor_temperature_M1": 15.0,
          "mixer_motor_temperature_M2": 18.2,
          "mixer_speed_M1": 20.4431,
          "mixer_speed_M2": 20.346,
          "mixer_torque_M1": 2.1146,
          "mixer_torque_M2": 2.2278
     },
     "232": {
          "Time": "11:24:03.307",
          "mixer_motor_temperature_M1": 15.0,
          "mixer_motor_temperature_M2": 18.2,
          "mixer_speed_M1": 20.694,
          "mixer_speed_M2": 20.2549,
          "mixer_torque_M1": 2.4544,
          "mixer_torque_M2": 2.4166
     },
     "233": {
          "Time": "11:24:04.096",
          "mixer_motor_temperature_M1": 15.9,
          "mixer_motor_temperature_M2": 18.6,
          "mixer_speed_M1": 20.5096,
          "mixer_speed_M2": 20.3524,
          "mixer_torque_M1": 2.5299,
          "mixer_torque_M2": 1.9635
     },
     "234": {
          "Time": "11:24:04.855",
          "mixer_motor_temperature_M1": 14.8,
          "mixer_motor_temperature_M2": 18.6,
          "mixer_speed_M1": 20.3024,
          "mixer_speed_M2": 20.4335,
          "mixer_torque_M1": 2.039,
          "mixer_torque_M2": 2.6054
     },
     "235": {
          "Time": "11:24:05.598",
          "mixer_motor_temperature_M1": 15.4,
          "mixer_motor_temperature_M2": 18.6,
          "mixer_speed_M1": 20.2915,
          "mixer_speed_M2": 20.7647,
          "mixer_torque_M1": 2.3034,
          "mixer_torque_M2": 1.9635
     },
     "236": {
          "Time": "11:24:06.373",
          "mixer_motor_temperature_M1": 15.4,
          "mixer_motor_temperature_M2": 17.9,
          "mixer_speed_M1": 20.4415,
          "mixer_speed_M2": 20.2275,
          "mixer_torque_M1": 2.8698,
          "mixer_torque_M2": 2.039
     },
     "237": {
          "Time": "11:24:07.128",
          "mixer_motor_temperature_M1": 15.0,
          "mixer_motor_temperature_M2": 18.6,
          "mixer_speed_M1": 20.4523,
          "mixer_speed_M2": 20.9052,
          "mixer_torque_M1": 2.0768,
          "mixer_torque_M2": 2.039
     },
     "238": {
          "Time": "11:24:07.884",
          "mixer_motor_temperature_M1": 15.4,
          "mixer_motor_temperature_M2": 18.6,
          "mixer_speed_M1": 20.2859,
          "mixer_speed_M2": 20.5199,
          "mixer_torque_M1": 2.1146,
          "mixer_torque_M2": 2.681
     },
     "239": {
          "Time": "11:24:08.660",
          "mixer_motor_temperature_M1": 14.8,
          "mixer_motor_temperature_M2": 18.2,
          "mixer_speed_M1": 20.1689,
          "mixer_speed_M2": 20.1869,
          "mixer_torque_M1": 2.4922,
          "mixer_torque_M2": 3.625
     },
     "240": {
          "Time": "11:24:09.419",
          "mixer_motor_temperature_M1": 15.4,
          "mixer_motor_temperature_M2": 18.2,
          "mixer_speed_M1": 20.5686,
          "mixer_speed_M2": 20.2815,
          "mixer_torque_M1": 1.8125,
          "mixer_torque_M2": 2.3789
     },
     "241": {
          "Time": "11:24:10.194",
          "mixer_motor_temperature_M1": 15.0,
          "mixer_motor_temperature_M2": 18.4,
          "mixer_speed_M1": 20.5278,
          "mixer_speed_M2": 20.3925,
          "mixer_torque_M1": 2.0768,
          "mixer_torque_M2": 2.1523
     },
     "242": {
          "Time": "11:24:10.961",
          "mixer_motor_temperature_M1": 15.0,
          "mixer_motor_temperature_M2": 18.2,
          "mixer_speed_M1": 20.3268,
          "mixer_speed_M2": 20.58,
          "mixer_torque_M1": 2.3034,
          "mixer_torque_M2": 2.1901
     }
}