{
     "1": {
          "Time": "09:18:45.541",
          "mixer_motor_temperature_M1": 15.4,
          "mixer_motor_temperature_M2": 19.1,
          "mixer_speed_M1": 60.4372,
          "mixer_speed_M2": 60.0603,
          "mixer_torque_M1": 2.5677,
          "mixer_torque_M2": 2.5299
     },
     "2": {
          "Time": "09:18:46.504",
          "mixer_motor_temperature_M1": 15.7,
          "mixer_motor_temperature_M2": 19.1,
          "mixer_speed_M1": 59.8704,
          "mixer_speed_M2": 59.9139,
          "mixer_torque_M1": 2.5677,
          "mixer_torque_M2": 3.6627
     },
     "3": {
          "Time": "09:18:47.267",
          "mixer_motor_temperature_M1": 16.1,
          "mixer_motor_temperature_M2": 19.3,
          "mixer_speed_M1": 59.8925,
          "mixer_speed_M2": 60.2624,
          "mixer_torque_M1": 2.681,
          "mixer_torque_M2": 3.2474
     },
     "4": {
          "Time": "09:18:48.043",
          "mixer_motor_temperature_M1": 15.7,
          "mixer_motor_temperature_M2": 19.5,
          "mixer_speed_M1": 59.988,
          "mixer_speed_M2": 60.0149,
          "mixer_torque_M1": 3.2851,
          "mixer_torque_M2": 3.3229
     },
     "5": {
          "Time": "09:18:48.801",
          "mixer_motor_temperature_M1": 15.2,
          "mixer_motor_temperature_M2": 19.3,
          "mixer_speed_M1": 59.8431,
          "mixer_speed_M2": 61.205,
          "mixer_torque_M1": 2.4166,
          "mixer_torque_M2": 3.3984
     },
     "6": {
          "Time": "09:18:49.560",
          "mixer_motor_temperature_M1": 15.2,
          "mixer_motor_temperature_M2": 19.5,
          "mixer_speed_M1": 60.1223,
          "mixer_speed_M2": 59.9371,
          "mixer_torque_M1": 2.2278,
          "mixer_torque_M2": 2.8698
     },
     "7": {
          "Time": "09:18:50.318",
          "mixer_motor_temperature_M1": 15.7,
          "mixer_motor_temperature_M2": 19.5,
          "mixer_speed_M1": 59.7888,
          "mixer_speed_M2": 60.2266,
          "mixer_torque_M1": 2.983,
          "mixer_torque_M2": 4.0781
     },
     "8": {
          "Time": "09:18:51.080",
          "mixer_motor_temperature_M1": 15.2,
          "mixer_motor_temperature_M2": 19.8,
          "mixer_speed_M1": 60.3789,
          "mixer_speed_M2": 60.0778,
          "mixer_torque_M1": 2.681,
          "mixer_torque_M2": 3.927
     },
     "9": {
          "Time": "09:18:51.839",
          "mixer_motor_temperature_M1": 16.1,
          "mixer_motor_temperature_M2": 19.5,
          "mixer_speed_M1": 60.6409,
          "mixer_speed_M2": 59.9341,
          "mixer_torque_M1": 2.5677,
          "mixer_torque_M2": 3.8515
     },
     "10": {
          "Time": "09:18:52.601",
          "mixer_motor_temperature_M1": 15.9,
          "mixer_motor_temperature_M2": 19.1,
          "mixer_speed_M1": 60.0936,
          "mixer_speed_M2": 59.6355,
          "mixer_torque_M1": 3.5872,
          "mixer_torque_M2": 3.2096
     },
     "11": {
          "Time": "09:18:53.365",
          "mixer_motor_temperature_M1": 15.9,
          "mixer_motor_temperature_M2": 19.3,
          "mixer_speed_M1": 60.0024,
          "mixer_speed_M2": 59.6104,
          "mixer_torque_M1": 2.9075,
          "mixer_torque_M2": 3.8515
     },
     "12": {
          "Time": "09:18:54.128",
          "mixer_motor_temperature_M1": 16.1,
          "mixer_motor_temperature_M2": 19.1,
          "mixer_speed_M1": 59.8485,
          "mixer_speed_M2": 59.9651,
          "mixer_torque_M1": 2.7942,
          "mixer_torque_M2": 3.7005
     },
     "13": {
          "Time": "09:18:54.885",
          "mixer_motor_temperature_M1": 15.7,
          "mixer_motor_temperature_M2": 19.5,
          "mixer_speed_M1": 60.1508,
          "mixer_speed_M2": 59.8685,
          "mixer_torque_M1": 2.3789,
          "mixer_torque_M2": 3.927
     },
     "14": {
          "Time": "09:18:55.642",
          "mixer_motor_temperature_M1": 15.9,
          "mixer_motor_temperature_M2": 19.5,
          "mixer_speed_M1": 60.0766,
          "mixer_speed_M2": 60.2727,
          "mixer_torque_M1": 2.039,
          "mixer_torque_M2": 2.832
     },
     "15": {
          "Time": "09:18:56.401",
          "mixer_motor_temperature_M1": 16.3,
          "mixer_motor_temperature_M2": 19.3,
          "mixer_speed_M1": 59.8307,
          "mixer_speed_M2": 59.9803,
          "mixer_torque_M1": 2.1146,
          "mixer_torque_M2": 3.5117
     },
     "16": {
          "Time": "09:18:57.157",
          "mixer_motor_temperature_M1": 15.7,
          "mixer_motor_temperature_M2": 19.1,
          "mixer_speed_M1": 59.93,
          "mixer_speed_M2": 59.9293,
          "mixer_torque_M1": 2.4544,
          "mixer_torque_M2": 3.0963
     },
     "17": {
          "Time": "09:18:57.915",
          "mixer_motor_temperature_M1": 16.1,
          "mixer_motor_temperature_M2": 19.5,
          "mixer_speed_M1": 119.8174,
          "mixer_speed_M2": 119.6371,
          "mixer_torque_M1": 3.0586,
          "mixer_torque_M2": 4.1158
     },
     "18": {
          "Time": "09:18:58.671",
          "mixer_motor_temperature_M1": 16.1,
          "mixer_motor_temperature_M2": 19.1,
          "mixer_speed_M1": 119.5786,
          "mixer_speed_M2": 119.9219,
          "mixer_torque_M1": 4.3802,
          "mixer_torque_M2": 5.3619
     },
     "19": {
          "Time": "09:18:59.435",
          "mixer_motor_temperature_M1": 15.9,
          "mixer_motor_temperature_M2": 19.1,
          "mixer_speed_M1": 120.0527,
          "mixer_speed_M2": 120.2565,
          "mixer_torque_M1": 3.1718,
          "mixer_torque_M2": 4.1914
     },
     "20": {
          "Time": "09:19:00.193",
          "mixer_motor_temperature_M1": 15.2,
          "mixer_motor_temperature_M2": 19.3,
          "mixer_speed_M1": 119.4762,
          "mixer_speed_M2": 119.9534,
          "mixer_torque_M1": 4.0026,
          "mixer_torque_M2": 4.72
     },
     "21": {
          "Time": "09:19:00.953",
          "mixer_motor_temperature_M1": 15.9,
          "mixer_motor_temperature_M2": 19.1,
          "mixer_speed_M1": 119.9736,
          "mixer_speed_M2": 119.5309,
          "mixer_torque_M1": 3.3229,
          "mixer_torque_M2": 4.1536
     },
     "22": {
          "Time": "09:19:01.712",
          "mixer_motor_temperature_M1": 15.9,
          "mixer_motor_temperature_M2": 19.1,
          "mixer_speed_M1": 120.0688,
          "mixer_speed_M2": 119.8194,
          "mixer_torque_M1": 3.7382,
          "mixer_torque_M2": 4.8333
     },
     "23": {
          "Time": "09:19:02.479",
          "mixer_motor_temperature_M1": 15.4,
          "mixer_motor_temperature_M2": 19.1,
          "mixer_speed_M1": 120.3021,
          "mixer_speed_M2": 120.6043,
          "mixer_torque_M1": 2.7565,
          "mixer_torque_M2": 3.8515
     },
     "24": {
          "Time": "09:19:03.236",
          "mixer_motor_temperature_M1": 15.4,
          "mixer_motor_temperature_M2": 19.1,
          "mixer_speed_M1": 119.6856,
          "mixer_speed_M2": 119.9698,
          "mixer_torque_M1": 3.6627,
          "mixer_torque_M2": 4.871
     },
     "25": {
          "Time": "09:19:03.989",
          "mixer_motor_temperature_M1": 15.7,
          "mixer_motor_temperature_M2": 19.3,
          "mixer_speed_M1": 120.2277,
          "mixer_speed_M2": 119.6404,
          "mixer_torque_M1": 3.3229,
          "mixer_torque_M2": 3.3984
     },
     "26": {
          "Time": "09:19:04.748",
          "mixer_motor_temperature_M1": 15.4,
          "mixer_motor_temperature_M2": 19.5,
          "mixer_speed_M1": 120.9556,
          "mixer_speed_M2": 119.911,
          "mixer_torque_M1": 4.3424,
          "mixer_torque_M2": 3.7382
     },
     "27": {
          "Time": "09:19:05.527",
          "mixer_motor_temperature_M1": 15.4,
          "mixer_motor_temperature_M2": 19.5,
          "mixer_speed_M1": 120.0128,
          "mixer_speed_M2": 120.01,
          "mixer_torque_M1": 3.1718,
          "mixer_torque_M2": 4.1914
     },
     "28": {
          "Time": "09:19:06.290",
          "mixer_motor_temperature_M1": 15.9,
          "mixer_motor_temperature_M2": 19.3,
          "mixer_speed_M1": 119.7929,
          "mixer_speed_M2": 119.9163,
          "mixer_torque_M1": 3.4739,
          "mixer_torque_M2": 3.927
     },
     "29": {
          "Time": "09:19:07.054",
          "mixer_motor_temperature_M1": 15.9,
          "mixer_motor_temperature_M2": 19.5,
          "mixer_speed_M1": 119.9796,
          "mixer_speed_M2": 120.1917,
          "mixer_torque_M1": 3.2474,
          "mixer_torque_M2": 4.3802
     },
     "30": {
          "Time": "09:19:07.834",
          "mixer_motor_temperature_M1": 16.8,
          "mixer_motor_temperature_M2": 19.1,
          "mixer_speed_M1": 119.8239,
          "mixer_speed_M2": 119.7603,
          "mixer_torque_M1": 3.2474,
          "mixer_torque_M2": 4.4179
     },
     "31": {
          "Time": "09:19:08.598",
          "mixer_motor_temperature_M1": 16.1,
          "mixer_motor_temperature_M2": 19.5,
          "mixer_speed_M1": 120.1956,
          "mixer_speed_M2": 119.5828,
          "mixer_torque_M1": 3.2851,
          "mixer_torque_M2": 3.9648
     },
     "32": {
          "Time": "09:19:09.358",
          "mixer_motor_temperature_M1": 15.9,
          "mixer_motor_temperature_M2": 19.1,
          "mixer_speed_M1": 120.9953,
          "mixer_speed_M2": 119.9339,
          "mixer_torque_M1": 3.8138,
          "mixer_torque_M2": 3.5872
     },
     "33": {
          "Time": "09:19:10.121",
          "mixer_motor_temperature_M1": 15.9,
          "mixer_motor_temperature_M2": 19.3,
          "mixer_speed_M1": 120.1335,
          "mixer_speed_M2": 121.0429,
          "mixer_torque_M1": 3.5872,
          "mixer_torque_M2": 4.7955
     },
     "34": {
          "Time": "09:19:10.883",
          "mixer_motor_temperature_M1": 16.3,
          "mixer_motor_temperature_M2": 19.5,
          "mixer_speed_M1": 120.0342,
          "mixer_speed_M2": 119.8695,
          "mixer_torque_M1": 3.4739,
          "mixer_torque_M2": 4.72
     },
     "35": {
          "Time": "09:19:11.646",
          "mixer_motor_temperature_M1": 15.9,
          "mixer_motor_temperature_M2": 19.5,
          "mixer_speed_M1": 119.8642,
          "mixer_speed_M2": 119.9496,
          "mixer_torque_M1": 3.3984,
          "mixer_torque_M2": 4.4934
     },
     "36": {
          "Time": "09:19:12.407",
          "mixer_motor_temperature_M1": 15.9,
          "mixer_motor_temperature_M2": 19.1,
          "mixer_speed_M1": 120.1179,
          "mixer_speed_M2": 120.1535,
          "mixer_torque_M1": 2.6432,
          "mixer_torque_M2": 3.8893
     },
     "37": {
          "Time": "09:19:13.165",
          "mixer_motor_temperature_M1": 15.9,
          "mixer_motor_temperature_M2": 19.5,
          "mixer_speed_M1": 119.6143,
          "mixer_speed_M2": 120.3636,
          "mixer_torque_M1": 3.2474,
          "mixer_torque_M2": 3.927
     },
     "38": {
          "Time": "09:19:13.938",
          "mixer_motor_temperature_M1": 15.4,
          "mixer_motor_temperature_M2": 19.3,
          "mixer_speed_M1": 120.0248,
          "mixer_speed_M2": 119.9095,
          "mixer_torque_M1": 3.0963,
          "mixer_torque_M2": 4.0403
     },
     "39": {
          "Time": "09:19:14.700",
          "mixer_motor_temperature_M1": 16.1,
          "mixer_motor_temperature_M2": 19.5,
          "mixer_speed_M1": 119.522,
          "mixer_speed_M2": 120.2468,
          "mixer_torque_M1": 3.2474,
          "mixer_torque_M2": 4.3802
     },
     "40": {
          "Time": "09:19:15.464",
          "mixer_motor_temperature_M1": 16.6,
          "mixer_motor_temperature_M2": 19.5,
          "mixer_speed_M1": 120.3007,
          "mixer_speed_M2": 119.9724,
          "mixer_torque_M1": 3.0586,
          "mixer_torque_M2": 3.4362
     },
     "41": {
          "Time": "09:19:16.242",
          "mixer_motor_temperature_M1": 16.3,
          "mixer_motor_temperature_M2": 19.8,
          "mixer_speed_M1": 119.7762,
          "mixer_speed_M2": 119.9371,
          "mixer_torque_M1": 3.3984,
          "mixer_torque_M2": 3.8515
     },
     "42": {
          "Time": "09:19:16.993",
          "mixer_motor_temperature_M1": 15.9,
          "mixer_motor_temperature_M2": 19.3,
          "mixer_speed_M1": 120.1502,
          "mixer_speed_M2": 119.6823,
          "mixer_torque_M1": 3.625,
          "mixer_torque_M2": 3.3606
     },
     "43": {
          "Time": "09:19:17.754",
          "mixer_motor_temperature_M1": 15.4,
          "mixer_motor_temperature_M2": 19.5,
          "mixer_speed_M1": 119.9946,
          "mixer_speed_M2": 120.1499,
          "mixer_torque_M1": 3.8138,
          "mixer_torque_M2": 4.72
     },
     "44": {
          "Time": "09:19:18.518",
          "mixer_motor_temperature_M1": 16.3,
          "mixer_motor_temperature_M2": 19.5,
          "mixer_speed_M1": 120.1111,
          "mixer_speed_M2": 120.3737,
          "mixer_torque_M1": 2.9075,
          "mixer_torque_M2": 4.1536
     },
     "45": {
          "Time": "09:19:19.279",
          "mixer_motor_temperature_M1": 15.9,
          "mixer_motor_temperature_M2": 19.5,
          "mixer_speed_M1": 119.7787,
          "mixer_speed_M2": 120.123,
          "mixer_torque_M1": 3.6627,
          "mixer_torque_M2": 4.569
     },
     "46": {
          "Time": "09:19:20.040",
          "mixer_motor_temperature_M1": 17.5,
          "mixer_motor_temperature_M2": 19.5,
          "mixer_speed_M1": 120.0466,
          "mixer_speed_M2": 119.8133,
          "mixer_torque_M1": 3.2851,
          "mixer_torque_M2": 5.1354
     },
     "47": {
          "Time": "09:19:20.805",
          "mixer_motor_temperature_M1": 16.1,
          "mixer_motor_temperature_M2": 19.8,
          "mixer_speed_M1": 120.0265,
          "mixer_speed_M2": 119.7956,
          "mixer_torque_M1": 3.3606,
          "mixer_torque_M2": 4.0403
     },
     "48": {
          "Time": "09:19:21.563",
          "mixer_motor_temperature_M1": 15.9,
          "mixer_motor_temperature_M2": 19.8,
          "mixer_speed_M1": 120.0559,
          "mixer_speed_M2": 119.816,
          "mixer_torque_M1": 3.0208,
          "mixer_torque_M2": 4.1536
     },
     "49": {
          "Time": "09:19:22.321",
          "mixer_motor_temperature_M1": 15.4,
          "mixer_motor_temperature_M2": 19.5,
          "mixer_speed_M1": 120.1391,
          "mixer_speed_M2": 120.0013,
          "mixer_torque_M1": 3.3229,
          "mixer_torque_M2": 4.4557
     },
     "50": {
          "Time": "09:19:23.083",
          "mixer_motor_temperature_M1": 15.4,
          "mixer_motor_temperature_M2": 19.8,
          "mixer_speed_M1": 119.9605,
          "mixer_speed_M2": 119.3852,
          "mixer_torque_M1": 2.681,
          "mixer_torque_M2": 4.569
     },
     "51": {
          "Time": "09:19:23.857",
          "mixer_motor_temperature_M1": 15.2,
          "mixer_motor_temperature_M2": 19.5,
          "mixer_speed_M1": 119.4175,
          "mixer_speed_M2": 119.9169,
          "mixer_torque_M1": 3.0963,
          "mixer_torque_M2": 3.6627
     },
     "52": {
          "Time": "09:19:24.618",
          "mixer_motor_temperature_M1": 15.7,
          "mixer_motor_temperature_M2": 19.5,
          "mixer_speed_M1": 120.4825,
          "mixer_speed_M2": 119.8381,
          "mixer_torque_M1": 3.1718,
          "mixer_torque_M2": 4.2291
     },
     "53": {
          "Time": "09:19:25.378",
          "mixer_motor_temperature_M1": 15.4,
          "mixer_motor_temperature_M2": 19.8,
          "mixer_speed_M1": 119.9754,
          "mixer_speed_M2": 120.3711,
          "mixer_torque_M1": 3.3606,
          "mixer_torque_M2": 4.4179
     },
     "54": {
          "Time": "09:19:26.149",
          "mixer_motor_temperature_M1": 16.1,
          "mixer_motor_temperature_M2": 19.5,
          "mixer_speed_M1": 119.9577,
          "mixer_speed_M2": 120.1847,
          "mixer_torque_M1": 3.4739,
          "mixer_torque_M2": 5.3242
     },
     "55": {
          "Time": "09:19:26.923",
          "mixer_motor_temperature_M1": 16.6,
          "mixer_motor_temperature_M2": 19.5,
          "mixer_speed_M1": 119.9537,
          "mixer_speed_M2": 120.2115,
          "mixer_torque_M1": 2.832,
          "mixer_torque_M2": 3.776
     },
     "56": {
          "Time": "09:19:27.686",
          "mixer_motor_temperature_M1": 15.9,
          "mixer_motor_temperature_M2": 19.5,
          "mixer_speed_M1": 119.9808,
          "mixer_speed_M2": 119.187,
          "mixer_torque_M1": 4.1536,
          "mixer_torque_M2": 4.6445
     },
     "57": {
          "Time": "09:19:28.452",
          "mixer_motor_temperature_M1": 17.3,
          "mixer_motor_temperature_M2": 19.5,
          "mixer_speed_M1": 119.9399,
          "mixer_speed_M2": 119.8245,
          "mixer_torque_M1": 2.7187,
          "mixer_torque_M2": 3.7382
     },
     "58": {
          "Time": "09:19:29.207",
          "mixer_motor_temperature_M1": 16.1,
          "mixer_motor_temperature_M2": 19.8,
          "mixer_speed_M1": 119.7225,
          "mixer_speed_M2": 120.145,
          "mixer_torque_M1": 3.8138,
          "mixer_torque_M2": 4.2669
     },
     "59": {
          "Time": "09:19:29.964",
          "mixer_motor_temperature_M1": 15.9,
          "mixer_motor_temperature_M2": 19.1,
          "mixer_speed_M1": 120.1496,
          "mixer_speed_M2": 119.9443,
          "mixer_torque_M1": 2.5299,
          "mixer_torque_M2": 3.3984
     },
     "60": {
          "Time": "09:19:30.725",
          "mixer_motor_temperature_M1": 15.9,
          "mixer_motor_temperature_M2": 20.0,
          "mixer_speed_M1": 119.9735,
          "mixer_speed_M2": 119.785,
          "mixer_torque_M1": 3.1718,
          "mixer_torque_M2": 3.8138
     }
}